{
  "generated_at": "2026-03-12T10:21:53.254060Z",
  "total": 147,
  "events": [
    {
      "id": "gdelt-1658643847",
      "source": "gdelt",
      "category": "conflict",
      "title": "Palestinian Citizen of Israel Jailed for Criticism of the War on Iran",
      "country": "Israel",
      "url": "https://www.counterpunch.org/2026/03/12/palestinian-citizen-of-israel-jailed-for-criticism-of-the-war-on-iran/",
      "source_name": "counterpunch.org",
      "timestamp": "20260312T091500Z",
      "language": "English",
      "image": "https://www.counterpunch.org/wp-content/uploads/2026/03/word-image-403778-1.png",
      "lat": 31.05,
      "lng": 34.85
    },
    {
      "id": "gdelt-1788956771",
      "source": "gdelt",
      "category": "conflict",
      "title": "Qué hay detrás de la Guerra de Medio Oriente y qué busca cada país involucrado",
      "country": "",
      "url": "https://www.lanacion.com.ar/el-mundo/que-hay-detras-de-la-guerra-de-medio-oriente-y-que-busca-cada-pais-involucrado-nid11032026/",
      "source_name": "lanacion.com.ar",
      "timestamp": "20260312T091500Z",
      "language": "Spanish",
      "image": "https://resizer.glanacion.com/resizer/v2/la-influencia-de-la-guerra-en-iran-sobre-los-4K572DO3QRFDJE466R2PPEYENY.jpg?auth=28fde4856dcac36d4a7ac75c4c35165e02b329aa3ea90259039312a42e7ef322&quality=85&smart=true",
      "lat": null,
      "lng": null
    },
    {
      "id": "gdelt-455274228",
      "source": "gdelt",
      "category": "conflict",
      "title": "Libano : le chiese del nord accolgono gli sfollati dal sud . Padre Makari :  Hanno perso tutto ancora una volta  ",
      "country": "",
      "url": "https://www.agensir.it/mondo/2026/03/12/libano-le-chiese-del-nord-accolgono-gli-sfollati-dal-sud-padre-makari-hanno-perso-tutto-ancora-una-volta/",
      "source_name": "agensir.it",
      "timestamp": "20260312T091500Z",
      "language": "Italian",
      "image": "https://www.agensir.it/wp-content/uploads/2026/03/Health-Campaign-6-3-26-a-755x491.jpg",
      "lat": null,
      "lng": null
    },
    {
      "id": "gdelt-482739597",
      "source": "gdelt",
      "category": "conflict",
      "title": "Amíg aludtunk Dél - Korea ledobta a bombát : ilyen pontos fegyver még nem járt a Közel - Keleten",
      "country": "",
      "url": "https://www.vg.hu/nemzetkozi-gazdasag/2026/03/del-korea-egyesult-arab-emirsegek-izrael-allamok",
      "source_name": "vg.hu",
      "timestamp": "20260312T091500Z",
      "language": "Hungarian",
      "image": "https://cdn.vg.hu/2026/03/auvikD8ncduAokCCEKevOPc9Xw6OdA9LoCs_nKbTfN8/fill/1200/675/no/1/aHR0cHM6Ly9jbXNjZG4uYXBwLmNvbnRlbnQucHJpdmF0ZS9jb250ZW50LzYxYTE3NzY0MDg3NzQ0ZGM4ZjQyZWQyZDAzMTczYWMy.jpg",
      "lat": null,
      "lng": null
    },
    {
      "id": "gdelt-3556486023",
      "source": "gdelt",
      "category": "conflict",
      "title": "Japan to Release Oil Reserves Early Over Mideast Conflict",
      "country": "",
      "url": "https://www.newkerala.com/news/a/japan-begin-drawing-down-oil-reserves-as-early-472.htm",
      "source_name": "newkerala.com",
      "timestamp": "20260312T091500Z",
      "language": "English",
      "image": "https://one.newkerala.com/images/t/newkerala-com-news250.webp",
      "lat": null,
      "lng": null
    },
    {
      "id": "gdelt-741505319",
      "source": "gdelt",
      "category": "conflict",
      "title": "Habervitrini . com | İsrailliler sığınaklardan çıkamıyor ekonomik kriz kapıda",
      "country": "",
      "url": "https://www.habervitrini.com/israilliler-siginaklardan-cikamiyor-ekonomik-kriz-kapida/1159186",
      "source_name": "habervitrini.com",
      "timestamp": "20260312T091500Z",
      "language": "Turkish",
      "image": "https://img.habervitrini.com/Haber/_AnaManset/2fb5958e-6069-4335-b062-3b23f5d7d21c.jpg",
      "lat": null,
      "lng": null
    },
    {
      "id": "gdelt-1712558083",
      "source": "gdelt",
      "category": "conflict",
      "title": "Los cataplines de Donald",
      "country": "",
      "url": "https://www.eldia.es/opinion/2026/03/12/cataplines-donald-127851221.html",
      "source_name": "eldia.es",
      "timestamp": "20260312T091500Z",
      "language": "Spanish",
      "image": "https://estaticos-cdn.prensaiberica.es/clip/5e23afa9-588a-4531-91f4-4ea91d4729f9_16-9-discover-aspect-ratio_default_0_x1200y533.jpg",
      "lat": null,
      "lng": null
    },
    {
      "id": "gdelt-862421855",
      "source": "gdelt",
      "category": "conflict",
      "title": "Oil tankers struck off Iraq coast as person dead in huge explosion",
      "country": "Iraq",
      "url": "https://www.dailyrecord.co.uk/news/uk-world-news/oil-tankers-struck-iraq-coast-36854197",
      "source_name": "dailyrecord.co.uk",
      "timestamp": "20260312T091500Z",
      "language": "English",
      "image": "https://i2-prod.dailyrecord.co.uk/article36854200.ece/ALTERNATES/s1200d/1_Explosion-Dubai.jpg",
      "lat": 33.22,
      "lng": 43.68
    },
    {
      "id": "gdelt-1675941233",
      "source": "gdelt",
      "category": "conflict",
      "title": "Lufthansa - Streik heute und Freitag : Das müssen Reisende aktuell wissen",
      "country": "",
      "url": "https://www.dewezet.de/reise/lufthansa-streik-heute-und-freitag-das-muessen-reisende-aktuell-wissen-4ZL6QGEBWRDXDEIBKWDCRWREQQ.html",
      "source_name": "dewezet.de",
      "timestamp": "20260312T091500Z",
      "language": "German",
      "image": "https://www.dewezet.de/resizer/v2/ZGIVURV7RNFU7AOAEBJJ7OLXPI.jpg?auth=471d644ed8df461421681a64b9036dd5f78a5a5d23acec3c096ee30b417f2620&quality=70&smart=true",
      "lat": null,
      "lng": null
    },
    {
      "id": "gdelt-2442769186",
      "source": "gdelt",
      "category": "conflict",
      "title": "CHPli Bağcıoğlu :  Çelik Kubbe Hava Savunma Sistemi İlave Kaynak Tahsis Edilerek Hızlandırılmalı  ",
      "country": "",
      "url": "http://www.haberler.com/guncel/chp-li-bagcioglu-celik-kubbe-hava-savunma-sistemi-19649775-haberi/",
      "source_name": "haberler.com",
      "timestamp": "20260312T091500Z",
      "language": "Turkish",
      "image": "",
      "lat": null,
      "lng": null
    },
    {
      "id": "gdelt-817337962",
      "source": "gdelt",
      "category": "conflict",
      "title": "Habervitrini . com | Beyrut taki sahil şeridine düzenlenen hava saldırısında sekiz kişi öldü . ",
      "country": "",
      "url": "https://www.habervitrini.com/beyruttaki-sahil-seridine-duzenlenen-hava-saldirisinda-sekiz-kisi-oldu/1159181",
      "source_name": "habervitrini.com",
      "timestamp": "20260312T091500Z",
      "language": "Turkish",
      "image": "https://img.habervitrini.com/Haber/_AnaManset/58d84829-4461-41d3-9204-33fc80786dd8.jpg",
      "lat": null,
      "lng": null
    },
    {
      "id": "gdelt-1712776238",
      "source": "gdelt",
      "category": "conflict",
      "title": "Thank God for Global Capitalism",
      "country": "",
      "url": "https://www.counterpunch.org/2026/03/12/thank-god-for-global-capitalism/",
      "source_name": "counterpunch.org",
      "timestamp": "20260312T091500Z",
      "language": "English",
      "image": "https://www.counterpunch.org/wp-content/uploads/2026/01/Screenshot-2026-01-15-at-5.37.22-PM-828x630.png",
      "lat": null,
      "lng": null
    },
    {
      "id": "gdelt-1462539730",
      "source": "gdelt",
      "category": "conflict",
      "title": "Frappe nocturne à Erbil en Irak : le gouvernement italien fixe le sort de ses militaires visés par un missile",
      "country": "",
      "url": "https://senego.com/frappe-nocturne-a-erbil-en-irak-le-gouvernement-italien-fixe-le-sort-de-ses-militaires-vises-par-un-missile_1936394.html",
      "source_name": "senego.com",
      "timestamp": "20260312T091500Z",
      "language": "French",
      "image": "https://senego.com/wp-content/uploads/2026/03/1773303991_thumbs_b_c_717625ca6d6124cae1bb372459bef9c9.jpg",
      "lat": null,
      "lng": null
    },
    {
      "id": "gdelt-2251157903",
      "source": "gdelt",
      "category": "conflict",
      "title": "Политолог объяснил , почему США не могут выйти из войны с Ираном",
      "country": "",
      "url": "https://news.mail.ru/politics/70126193/",
      "source_name": "news.mail.ru",
      "timestamp": "20260312T091500Z",
      "language": "Russian",
      "image": "https://resizer.mail.ru/p/3941bf63-3243-513b-bb03-f1857e1143f3/AQAGh5RFFbCFNsh-YOBsHHxgo5v1MzpUCzOIAp2ou8qyhph8RYJFI6szW4BJ2iPZbzIJTctZCk0qY6SG9GYOBUJz3oI.jpg",
      "lat": null,
      "lng": null
    },
    {
      "id": "gdelt-2559990256",
      "source": "gdelt",
      "category": "conflict",
      "title": "US may seek exit from Iran war by moving the goalposts of victory",
      "country": "Iran",
      "url": "https://www.hani.co.kr/arti/english_edition/e_international/1249030.html",
      "source_name": "hani.co.kr",
      "timestamp": "20260312T091500Z",
      "language": "English",
      "image": "https://flexible.img.hani.co.kr/flexible/normal/894/578/imgdb/original/2026/0312/6917733030116757.webp",
      "lat": 32.43,
      "lng": 53.69
    },
    {
      "id": "gdelt-3486993682",
      "source": "gdelt",
      "category": "conflict",
      "title": "Bijeg od rata : Bogataši na Bliskom istoku plaćaju golem novac za privatne letove",
      "country": "",
      "url": "https://www.index.hr/vijesti/clanak/bijeg-od-rata-bogatasi-na-bliskom-istoku-placaju-golem-novac-za-privatne-letove/2770305.aspx",
      "source_name": "index.hr",
      "timestamp": "20260312T091500Z",
      "language": "Croatian",
      "image": "https://ip.index.hr/remote/bucket.index.hr/b/index/12c1dd17-f337-4aaa-83e4-5322652017f9.png?fb_wtrmrk=vijesti.jpg&mode=crop&format=png",
      "lat": null,
      "lng": null
    },
    {
      "id": "gdelt-314503029",
      "source": "gdelt",
      "category": "conflict",
      "title": "Βηρυτός : Χτύπημα με drone - Οκτώ νεκροί και τραυματίες ( ΒΙΝΤΕΟ ) ",
      "country": "",
      "url": "https://www.offsite.com.cy/eidiseis/diethni/birytos-htypima-me-drone-okto-nekroi-kai-traymaties-binteo",
      "source_name": "offsite.com.cy",
      "timestamp": "20260312T091500Z",
      "language": "Greek",
      "image": "https://www.offsite.com.cy/sites/default/files/2026-03/7293daae8d532a3228ea885051834bdc_xl.jpg",
      "lat": null,
      "lng": null
    },
    {
      "id": "gdelt-2190630793",
      "source": "gdelt",
      "category": "conflict",
      "title": " [ Column ] Misconceptions about America war with Iran",
      "country": "Iran",
      "url": "https://www.hani.co.kr/arti/english_edition/english_editorials/1249031.html",
      "source_name": "hani.co.kr",
      "timestamp": "20260312T091500Z",
      "language": "English",
      "image": "https://flexible.img.hani.co.kr/flexible/normal/800/533/imgdb/original/2026/0312/291773303342861.webp",
      "lat": 32.43,
      "lng": 53.69
    },
    {
      "id": "gdelt-1978083688",
      "source": "gdelt",
      "category": "conflict",
      "title": "AP News Summary at 3 : 19 a . m . EDT - Harrison Daily",
      "country": "",
      "url": "http://harrisondaily.com/stories/ap-news-summary-at-319-am-edt,366811",
      "source_name": "harrisondaily.com",
      "timestamp": "20260312T091500Z",
      "language": "English",
      "image": "",
      "lat": null,
      "lng": null
    },
    {
      "id": "gdelt-2545475876",
      "source": "gdelt",
      "category": "conflict",
      "title": "İsrailin Beyrutun Sahil Bölgesine Saldırısında En Az 7 Kişi Öldü",
      "country": "",
      "url": "https://www.haberler.com/guncel/israil-in-beyrut-a-hava-saldirisinda-can-kaybi-19649340-haberi/",
      "source_name": "haberler.com",
      "timestamp": "20260312T091500Z",
      "language": "Turkish",
      "image": "",
      "lat": null,
      "lng": null
    },
    {
      "id": "gdelt-3066403124",
      "source": "gdelt",
      "category": "conflict",
      "title": "أشد من حرب العراق .. كيف تحكي صور الأقمار الصناعية قصة الساعات الأولى لحرب إيران ؟ ",
      "country": "",
      "url": "https://www.aljazeera.net/politics/2026/3/12/%D8%A3%D8%B4%D8%AF-%D9%85%D9%86-%D8%AD%D8%B1%D8%A8-%D8%A7%D9%84%D8%B9%D8%B1%D8%A7%D9%82-%D9%83%D9%8A%D9%81-%D8%AA%D8%AD%D9%83%D9%8A-%D8%B5%D9%88%D8%B1-%D8%A7%D9%84%D8%A3%D9%82%D9%85%D8%A7%D8%B1",
      "source_name": "aljazeera.net",
      "timestamp": "20260312T091500Z",
      "language": "Arabic",
      "image": "",
      "lat": null,
      "lng": null
    },
    {
      "id": "gdelt-454245224",
      "source": "gdelt",
      "category": "conflict",
      "title": "Πύραυλος χτύπησε ιταλική βάση στο βόρειο Ιράκ - Δεν υπάρχουν τραυματίες , δήλωσε ο Ιταλός ΥΠΕΞ",
      "country": "",
      "url": "https://www.tanea.gr/2026/03/12/world/pyraylos-xtypise-italiki-vasi-sto-voreio-irak-den-yparxoun-traymaties-dilose-o-italos-ypeks/",
      "source_name": "tanea.gr",
      "timestamp": "20260312T091500Z",
      "language": "Greek",
      "image": "https://www.tanea.gr/wp-content/uploads/2026/03/Missile.jpg",
      "lat": null,
      "lng": null
    },
    {
      "id": "gdelt-200053429",
      "source": "gdelt",
      "category": "conflict",
      "title": "NYP : система ПРО Израиля за сутки перехватила лишь половину ракет  Хезболлы  ",
      "country": "",
      "url": "https://www.vesti.ru/ns/nyp-sistema-pro-izrailya-za-sutki-perekhvatila-lish-polovinu-raket-khezbolly",
      "source_name": "vesti.ru",
      "timestamp": "20260312T091500Z",
      "language": "Russian",
      "image": "https://cdn.vesti.ru/photobank/prod/medium/866/554/4.jpg",
      "lat": null,
      "lng": null
    },
    {
      "id": "gdelt-499609980",
      "source": "gdelt",
      "category": "conflict",
      "title": "ABD istihbaratından İranda skandal ihmal ! Minabdaki ilkokul saldırısına ilişkin yeni detaylar ortaya çıktı",
      "country": "",
      "url": "https://www.ahaber.com.tr/galeri/dunya/abd-istihbaratindan-iranda-skandal-ihmal",
      "source_name": "ahaber.com.tr",
      "timestamp": "20260312T091500Z",
      "language": "Turkish",
      "image": "https://iahbr.tmgrup.com.tr/album/2026/03/12/abd-istihbaratindan-iranda-skandal-ihmal-1773291777257.jpg",
      "lat": null,
      "lng": null
    },
    {
      "id": "gdelt-1227639460",
      "source": "gdelt",
      "category": "conflict",
      "title": "US To Provide 172 Million Barrels To IEA Oil Reserve Release",
      "country": "",
      "url": "http://www.milwaukeesun.com/news/278916881/us-to-provide-172-million-barrels-to-iea-oil-reserve-release",
      "source_name": "milwaukeesun.com",
      "timestamp": "20260312T091500Z",
      "language": "English",
      "image": "https://image.chitra.live/api/v1/wps/be93e0d/9d099b7b-4eef-4cc5-b7d8-b9592cc41664/0/MjgxMWNkMDMtY2E-600x315.jpg",
      "lat": null,
      "lng": null
    },
    {
      "id": "gdelt-1006484746",
      "source": "gdelt",
      "category": "conflict",
      "title": "За сутки в больницы доставили 179 пострадавших в результате войны с Ираном | MigNews - Новости Израиля и Мира на русском языке",
      "country": "",
      "url": "https://mignews.com/news/disasters/za-sutki-v-bolnicy-dostavili-179-postradavshih-v-rezultate-vojny-s-iranom.html",
      "source_name": "mignews.com",
      "timestamp": "20260312T091500Z",
      "language": "Russian",
      "image": "https://mignews.com/media/cache/be/fb/befb2dce79019ddc7b69c2b6256db095.jpg",
      "lat": null,
      "lng": null
    },
    {
      "id": "gdelt-3602389663",
      "source": "gdelt",
      "category": "conflict",
      "title": "Lángba borultak a hajók a tengeren : elszabadult az olaj ára , komoly bajba kerülhet az egész világ",
      "country": "",
      "url": "https://www.penzcentrum.hu/vilag/20260312/langba-borultak-a-hajok-a-tengeren-elszabadult-az-olaj-ara-komoly-bajba-kerulhet-az-egesz-vilag-1195159",
      "source_name": "penzcentrum.hu",
      "timestamp": "20260312T091500Z",
      "language": "Hungarian",
      "image": "https://cdn.penzcentrum.hu/images/articles/lead/2026/02/1771428034-F74dxbdJ6_lg.jpg",
      "lat": null,
      "lng": null
    },
    {
      "id": "gdelt-934178373",
      "source": "gdelt",
      "category": "conflict",
      "title": "  הבינה המלאכותית שלך טיפשה כמוך : אדרעי מטגן  עיתונאי  לבנוני שזייף סרטון",
      "country": "",
      "url": "https://ch10.co.il/news/1052162/",
      "source_name": "ch10.co.il",
      "timestamp": "20260312T091500Z",
      "language": "Hebrew",
      "image": "https://ch10.co.il/wp-content/uploads/F250302CG151.jpg",
      "lat": null,
      "lng": null
    },
    {
      "id": "gdelt-3607208521",
      "source": "gdelt",
      "category": "conflict",
      "title": "Tehran strikes ships , targets Dubai airport | The Arkansas Democrat - Gazette",
      "country": "Tehran",
      "url": "https://www.arkansasonline.com/news/2026/mar/12/tehran-strikes-ships-targets-dubai-airport/",
      "source_name": "arkansasonline.com",
      "timestamp": "20260312T091500Z",
      "language": "English",
      "image": "https://wehco.media.clients.ellingtoncms.com/imports/adg/photos/212425347_212423567-43ff9cbb664c4a6bbd2a4b308a6d3032_t1200.jpg?57a0c2296240c280e9492005c3cad63e7cbe80f4",
      "lat": 35.69,
      "lng": 51.39
    },
    {
      "id": "gdelt-375167489",
      "source": "gdelt",
      "category": "conflict",
      "title": "Iran war : What is happening on day 13 of US - Israel attacks ? ",
      "country": "Israel",
      "url": "https://www.aljazeera.com/news/2026/3/12/iran-war-what-is-happening-on-day-13-of-us-israel-attacks",
      "source_name": "aljazeera.com",
      "timestamp": "20260312T091500Z",
      "language": "English",
      "image": "https://www.aljazeera.com/wp-content/uploads/2026/03/2026-03-12T024026Z_63214044_RC2P2KAEYF7G_RTRMADP_3_IRAN-CRISIS-ISRAEL-1773286994.jpg",
      "lat": 31.05,
      "lng": 34.85
    },
    {
      "id": "gdelt-2117392612",
      "source": "gdelt",
      "category": "conflict",
      "title": "意大利驻伊拉克基地 遭导弹袭击幸无人伤 | 国际",
      "country": "",
      "url": "https://www.orientaldaily.com.my/news/international/2026/03/12/803558",
      "source_name": "orientaldaily.com.my",
      "timestamp": "20260312T091500Z",
      "language": "Chinese",
      "image": "",
      "lat": null,
      "lng": null
    },
    {
      "id": "gdelt-535042808",
      "source": "gdelt",
      "category": "conflict",
      "title": "Ιράν : « Ελέγχουμε τα στενά του Ορμουζ » ",
      "country": "",
      "url": "https://pelop.gr/iran-elegchoume-ta-stena-tou-ormouz/",
      "source_name": "pelop.gr",
      "timestamp": "20260312T091500Z",
      "language": "Greek",
      "image": "https://pelop.gr/wp-content/uploads/2026/03/ormouz.webp",
      "lat": null,
      "lng": null
    },
    {
      "id": "gdelt-2673528774",
      "source": "gdelt",
      "category": "conflict",
      "title": "The Latest : Key oil price spikes over $100 as Iranian attacks hit shipping",
      "country": "Iran",
      "url": "https://www.weny.com/wires/the-latest-key-oil-price-spikes-over-100-as-iranian-attacks-hit-shipping/article_e92b0dc1-6385-5bec-8ca3-c84dc8833eaa.html",
      "source_name": "weny.com",
      "timestamp": "20260312T091500Z",
      "language": "English",
      "image": "https://bloximages.chicago2.vip.townnews.com/weny.com/content/tncms/custom/image/6636d01f-0000-41aa-8620-1d85e9ad6555.jpg",
      "lat": 32.43,
      "lng": 53.69
    },
    {
      "id": "gdelt-2225061446",
      "source": "gdelt",
      "category": "conflict",
      "title": "لبنان والفاتيكان يبحثان سبل وقف التصعيد والحفاظ على الحضور المسيحي",
      "country": "",
      "url": "https://www.dostor.org/5453842",
      "source_name": "dostor.org",
      "timestamp": "20260312T091500Z",
      "language": "Arabic",
      "image": "",
      "lat": null,
      "lng": null
    },
    {
      "id": "gdelt-2705867287",
      "source": "gdelt",
      "category": "conflict",
      "title": "Unidentified attack targets container ship near UAE coast",
      "country": "",
      "url": "https://www.trend.az/world/arab/4163883.html",
      "source_name": "trend.az",
      "timestamp": "20260312T091500Z",
      "language": "English",
      "image": "https://www.trend.az/media/2026/03/11/ship_fire_tanker_fire.jpg",
      "lat": null,
      "lng": null
    },
    {
      "id": "gdelt-2932721203",
      "source": "gdelt",
      "category": "conflict",
      "title": "سپاه‌پاسداران : پایگاه‌های هوایی پالماخیم و عوبدا و مقر شین بت هدف حمله",
      "country": "",
      "url": "https://sputnik.af/20260312/23205676.html",
      "source_name": "sputnik.af",
      "timestamp": "20260312T091500Z",
      "language": "Persian",
      "image": "https://cdn1.img.sputnik.af/img/07ea/03/0c/23205522_7:0:633:352_2072x0_60_0_0_6a1fbc1d74a86175c989806d5d7ecbe1.jpg",
      "lat": null,
      "lng": null
    },
    {
      "id": "gdelt-1045458434",
      "source": "gdelt",
      "category": "conflict",
      "title": "Моджтаба Хаменеи действительно ранен - в Иране сказали , как он себя чувствует",
      "country": "",
      "url": "https://24tv.ua/geopolitics/ru/modzhtaba-hamenei-dejstvitelno-ranen-v-irane-skazali-kak-on-sebja-chuvstvuet_n3026762",
      "source_name": "24tv.ua",
      "timestamp": "20260312T091500Z",
      "language": "Russian",
      "image": "https://24tv.ua/resources/photos/news/202603/3026762.jpg?v=1773303610000",
      "lat": null,
      "lng": null
    },
    {
      "id": "gdelt-3400908081",
      "source": "gdelt",
      "category": "conflict",
      "title": " « Σε εξαιρετική φόρμα » τα Στενά του Ορμούζ , λέει ο Τραμπ - Σώοι οι 22 ναυτικοί του ελληνόκτητου τάνκερ",
      "country": "",
      "url": "https://ikypros.com/?p=691611",
      "source_name": "ikypros.com",
      "timestamp": "20260312T091500Z",
      "language": "Greek",
      "image": "https://ikypros.com/wp-content/uploads/2026/03/363fdafd-ap26070631609008-og.jpg",
      "lat": null,
      "lng": null
    },
    {
      "id": "gdelt-549643455",
      "source": "gdelt",
      "category": "conflict",
      "title": "三股力量牵动局势 全球油市何去何从 ？ | 财经",
      "country": "",
      "url": "https://www.orientaldaily.com.my/news/business/2026/03/12/803559",
      "source_name": "orientaldaily.com.my",
      "timestamp": "20260312T091500Z",
      "language": "Chinese",
      "image": "https://www.orientaldaily.com.my/storage/resize_cache/images/uploads/news-cover/7F02CB22DBB7A99063AC4DCFA2C47E9E_low_1.jpg/e13adf4fc30ffe657c6a28675e375189.jpg",
      "lat": null,
      "lng": null
    },
    {
      "id": "gdelt-3567286703",
      "source": "gdelt",
      "category": "conflict",
      "title": "U . S . destroys several Iranian aircraft ( VIDEO ) ",
      "country": "Iran",
      "url": "https://www.trend.az/world/us/4163877.html",
      "source_name": "trend.az",
      "timestamp": "20260312T091500Z",
      "language": "English",
      "image": "https://www.trend.az/media/2026/03/12/us_plane.jpg",
      "lat": 32.43,
      "lng": 53.69
    },
    {
      "id": "gdelt-3437635168",
      "source": "gdelt",
      "category": "conflict",
      "title": "Guerra Iran - Israele - Usa , gli aggiornamenti di oggi 12 marzo 2026",
      "country": "Iran",
      "url": "https://www.italpress.com/guerra-iran-israele-usa-libano-aggiornamenti-oggi-12-marzo-diretta-live/",
      "source_name": "italpress.com",
      "timestamp": "20260312T091500Z",
      "language": "Italian",
      "image": "https://www.italpress.com/wp-content/uploads/2026/03/IPA_Agency_IPA72522941.jpg",
      "lat": 32.43,
      "lng": 53.69
    },
    {
      "id": "gdelt-3392744741",
      "source": "gdelt",
      "category": "conflict",
      "title": "Italian Defense Minister confirms missile strike on base in Iraq Erbil",
      "country": "Iraq",
      "url": "https://www.trend.az/world/4163880.html",
      "source_name": "trend.az",
      "timestamp": "20260312T091500Z",
      "language": "English",
      "image": "https://www.trend.az/imagen/4163880",
      "lat": 33.22,
      "lng": 43.68
    },
    {
      "id": "gdelt-4081437856",
      "source": "gdelt",
      "category": "conflict",
      "title": "Trumptan İran mesajı : İşi bitirene kadar ayrılmayacağız ve bu çok hızlı olacak ; tüm gemileri batırdık , boğazlar çok iyi – Aktifhaber",
      "country": "Iran",
      "url": "https://aktifhaber.com/dunya/trumptan-iran-mesaji-isi-bitirene-kadar-ayrilmayacagiz-ve-bu-cok-hizli-olacak-tum-gemileri-batirdik-bogazlar-cok-iyi.html",
      "source_name": "aktifhaber.com",
      "timestamp": "20260312T091500Z",
      "language": "Turkish",
      "image": "https://aktifhaber.com/wp-content/uploads/2026/03/Trumptan-Iran-mesaji.webp",
      "lat": 32.43,
      "lng": 53.69
    },
    {
      "id": "gdelt-3472425539",
      "source": "gdelt",
      "category": "conflict",
      "title": "Κρίση στη Μέση Ανατολή : Απειλές για ολοκληρωτικό πόλεμο",
      "country": "",
      "url": "https://ikypros.com/?p=691590",
      "source_name": "ikypros.com",
      "timestamp": "20260312T091500Z",
      "language": "Greek",
      "image": "https://ikypros.com/wp-content/uploads/2026/03/lebanon_bombing_ap26070820527466.jpg",
      "lat": null,
      "lng": null
    },
    {
      "id": "gdelt-1046306023",
      "source": "gdelt",
      "category": "conflict",
      "title": "Clouds of War in the Middle East",
      "country": "",
      "url": "https://www.counterpunch.org/2026/03/12/clouds-of-war-in-the-middle-east/",
      "source_name": "counterpunch.org",
      "timestamp": "20260312T091500Z",
      "language": "English",
      "image": "https://www.counterpunch.org/wp-content/uploads/2026/03/a-group-of-people-in-front-of-a-destroyed-building.jpeg",
      "lat": null,
      "lng": null
    },
    {
      "id": "gdelt-1521628125",
      "source": "gdelt",
      "category": "conflict",
      "title": "  Israel made a huge mistake : Did Kim Jong Un react after Israel North Korea embassy attack in Iran ? Here what happened",
      "country": "Israel",
      "url": "https://economictimes.indiatimes.com/news/new-updates/israel-made-a-huge-mistake-did-kim-jong-un-react-after-israels-north-korea-embassy-attack-in-iran-heres-what-happened/articleshow/129497957.cms",
      "source_name": "economictimes.indiatimes.com",
      "timestamp": "20260312T091500Z",
      "language": "English",
      "image": "https://img.etimg.com/thumb/msid-129498216,width-1200,height-630,imgsize-50762,overlay-economictimes/articleshow.jpg",
      "lat": 31.05,
      "lng": 34.85
    },
    {
      "id": "gdelt-4039207275",
      "source": "gdelt",
      "category": "conflict",
      "title": "A dor humana e o dano econômico",
      "country": "",
      "url": "https://oglobo.globo.com/blogs/miriam-leitao/coluna/2026/03/a-dor-humana-e-o-dano-economico.ghtml",
      "source_name": "oglobo.globo.com",
      "timestamp": "20260312T091500Z",
      "language": "Portuguese",
      "image": "https://s2-oglobo.glbimg.com/Q98Slwcu37a5_M37EceORewMWeE=/881x0/filters:format(jpeg)/https://i.s3.glbimg.com/v1/AUTH_da025474c0c44edd99332dddb09cabe8/internal_photos/bs/2026/e/h/dnQmEMTqW2vk8wijXAAw/114067664-this-picture-obtained-from-irans-isna-news-agency-shows-the-site-of-a-strike-on-a-girls.jpg",
      "lat": null,
      "lng": null
    },
    {
      "id": "gdelt-50050761",
      "source": "gdelt",
      "category": "conflict",
      "title": "Beyrutta A Haber kamerasına müdahale : Canlı yayında gergin anlar",
      "country": "",
      "url": "https://www.ahaber.com.tr/ozel-haberler/2026/03/12/beyrutta-a-haber-kamerasina-mudahale-canli-yayinda-gergin-anlar",
      "source_name": "ahaber.com.tr",
      "timestamp": "20260312T091500Z",
      "language": "Turkish",
      "image": "https://iahbr.tmgrup.com.tr/2026/03/12/beyrutta-a-haber-kamerasina-mudahale-canli-yayinda-gergin-anlar-1773301768223.jpeg",
      "lat": null,
      "lng": null
    },
    {
      "id": "gdelt-1542804974",
      "source": "gdelt",
      "category": "conflict",
      "title": "Amerikai célpontokat vehet célba Irán – az FBI már kiadta a figyelmeztetést Kaliforniában",
      "country": "",
      "url": "https://www.vg.hu/kozelet/2026/03/iran-haboru-amerikai-celpont-kalifornia-drontamadas",
      "source_name": "vg.hu",
      "timestamp": "20260312T091500Z",
      "language": "Hungarian",
      "image": "https://cdn.vg.hu/2026/03/ASLMpQB5K0pJ8F6BxrdVtebAfJIcG9dDS2vN1F83ICI/fill/1200/675/no/1/aHR0cHM6Ly9jbXNjZG4uYXBwLmNvbnRlbnQucHJpdmF0ZS9jb250ZW50L2RlY2UzMTc5ZjI2NzRmZTY5ZDc5ZGZlNzJlNWIxMWQ3.jpg",
      "lat": null,
      "lng": null
    },
    {
      "id": "gdelt-2816249956",
      "source": "gdelt",
      "category": "conflict",
      "title": "S - 400  ler füze tehdidine karşı neden kullanılmadı ? MSBden açıklama",
      "country": "",
      "url": "https://www.haber7.com/guncel/haber/3611364-s-400ler-fuze-tehdidine-karsi-neden-kullanilmadi-msbden-aciklama",
      "source_name": "haber7.com",
      "timestamp": "20260312T091500Z",
      "language": "Turkish",
      "image": "https://i20.haber7.net/resize/1280x720/haber/haber7/bigmanset/2026/11/msbden_kritik_guvenlik_hamlesi_patriotlar_devrede_1773305959_0085.jpg",
      "lat": null,
      "lng": null
    },
    {
      "id": "gdelt-1716752460",
      "source": "gdelt",
      "category": "protest",
      "title": "بالاترین : راهپیمایی روز قدس در لندن ممنوع شد",
      "country": "",
      "url": "https://www.balatarin.com:443/permlink/2026/3/11/6440592",
      "source_name": "balatarin.com",
      "timestamp": "20260312T091500Z",
      "language": "Persian",
      "image": "https://s3.amazonaws.com/bala.static/links/6440592.png",
      "lat": null,
      "lng": null
    },
    {
      "id": "gdelt-50749831",
      "source": "gdelt",
      "category": "protest",
      "title": "Azionario europeo in rosso con timori di shock petrolifero , a Milano corre Leonardo col piano",
      "country": "",
      "url": "https://www.borsaitaliana.it/borsa/notizie/teleborsa/finanza/azionario-europeo-in-rosso-con-timori-di-shock-petrolifero-a-milano-corre-leonardo-col-piano-3_2026-03-12_TLB-BIT.html",
      "source_name": "borsaitaliana.it",
      "timestamp": "20260312T091500Z",
      "language": "Italian",
      "image": "",
      "lat": null,
      "lng": null
    },
    {
      "id": "gdelt-2889993692",
      "source": "gdelt",
      "category": "protest",
      "title": "மோடி பீதியில் உள்ளார் - ராகுல் காந்தி .. பாராளுமன்ற வளாகத்தில் சிலிண்டர் தட்டுப்பாட்டை எதிர்த்து போராட்டம் - Modi is in panic - Rahul Gandhi .. Protest against cylinder shortage in Parliament premises",
      "country": "",
      "url": "https://www.maalaimalar.com:443/news/national/modi-is-in-panic-rahul-gandhi-protest-against-cylinder-shortage-in-parliament-premises-parliament-812948",
      "source_name": "maalaimalar.com",
      "timestamp": "20260312T091500Z",
      "language": "Tamil",
      "image": "https://media.maalaimalar.com/h-upload/2026/03/12/27314100-tn-29.jpg",
      "lat": null,
      "lng": null
    },
    {
      "id": "gdelt-1269189630",
      "source": "gdelt",
      "category": "protest",
      "title": "australia involvement in this trump shit is an embarrassment .... ",
      "country": "",
      "url": "https://yourdemocracy.net/drupal/node/58970",
      "source_name": "yourdemocracy.net",
      "timestamp": "20260312T091500Z",
      "language": "English",
      "image": "https://yourdemocracy.net/drupal/files/images/pumping%20watercash600%20copy%202.png",
      "lat": null,
      "lng": null
    },
    {
      "id": "gdelt-1941290157",
      "source": "gdelt",
      "category": "protest",
      "title": "广州法院去年共处理消费纠纷3 . 7万余件",
      "country": "",
      "url": "https://news.ycwb.com/ikimvkhtji/content_54005292.htm",
      "source_name": "news.ycwb.com",
      "timestamp": "20260312T091500Z",
      "language": "Chinese",
      "image": "https://news.ycwb.com/pic/2026-03/12/54005292_77e789da-34fb-4363-a3e7-cb85e192ea14.jpg",
      "lat": null,
      "lng": null
    },
    {
      "id": "gdelt-3507996710",
      "source": "gdelt",
      "category": "protest",
      "title": "Live updates : Oil price spikes again as Iran ship attacks surge",
      "country": "Iran",
      "url": "https://www.nbcnews.com/world/iran/live-blog/live-updates-iran-war-oil-ship-attacks-hormuz-trump-israel-lebanon-rcna263101",
      "source_name": "nbcnews.com",
      "timestamp": "20260312T091500Z",
      "language": "English",
      "image": "https://media-cldnry.s-nbcnews.com/image/upload/t_nbcnews-fp-1200-630,f_auto,q_auto:best/rockcms/2026-03/260312-ship-attack-rs-934e6f.jpg",
      "lat": 32.43,
      "lng": 53.69
    },
    {
      "id": "gdelt-3665989237",
      "source": "gdelt",
      "category": "protest",
      "title": "Vladari Irana stvorili sistem koji ih održava na vlasti",
      "country": "Iran",
      "url": "https://www.kurir.rs/planeta/9937891/vladari-irana-stvorili-sistem-koji-ih-odrzava-na-vlasti",
      "source_name": "kurir.rs",
      "timestamp": "20260312T091500Z",
      "language": "Serbian",
      "image": "https://static.kurir.rs/Picture/2506929/jpeg/profimedia-0946046513.jpg?ts=2026-03-06T22:08:26",
      "lat": 32.43,
      "lng": 53.69
    },
    {
      "id": "gdelt-1027327316",
      "source": "gdelt",
      "category": "protest",
      "title": "From helplessness to impact : Opening gateways for change",
      "country": "",
      "url": "https://ejewishphilanthropy.com/from-helplessness-to-impact-opening-gateways-for-change/",
      "source_name": "ejewishphilanthropy.com",
      "timestamp": "20260312T091500Z",
      "language": "English",
      "image": "https://image.ejewishphilanthropy.com/wp-content/uploads/2025/11/03002948/GettyImages-2186741355-e1762182131973.jpg",
      "lat": null,
      "lng": null
    },
    {
      "id": "gdelt-1028181340",
      "source": "gdelt",
      "category": "humanitarian",
      "title": "Οι Βρετανοί θυμούνται την Κρίση του Σουέζ",
      "country": "",
      "url": "https://www.capital.gr/diethni/3979150/oi-bretanoi-thumountai-tin-krisi-tou-souez/",
      "source_name": "capital.gr",
      "timestamp": "20260312T091500Z",
      "language": "Greek",
      "image": "https://www.capital.gr/Content/ImagesDatabase/fb/1000x523/crop/both/8b/8bab26e0c28c4f158ef0a7faa829e045.jpg",
      "lat": null,
      "lng": null
    },
    {
      "id": "gdelt-2650432782",
      "source": "gdelt",
      "category": "humanitarian",
      "title": "Cile proteste allinsediamento di Kast | bruciate bandiere united states e Israele",
      "country": "Israel",
      "url": "https://www.zazoom.it/2026-03-12/cile-proteste-allinsediamento-di-kast-bruciate-bandiere-usa-e-israele/18818094/",
      "source_name": "zazoom.it",
      "timestamp": "20260312T091500Z",
      "language": "Italian",
      "image": "https://img.lapresse.it/2026/03/12/12c940bf9c29d6252b0f5ea765c93a35.jpg",
      "lat": 31.05,
      "lng": 34.85
    },
    {
      "id": "gdelt-3331436711",
      "source": "gdelt",
      "category": "humanitarian",
      "title": "Damage to historical sites in Iran raises alarm about war impact on protected places",
      "country": "Iran",
      "url": "https://www.leadertelegram.com/news/world/damage-to-historical-sites-in-iran-raises-alarm-about-wars-impact-on-protected-places/article_7353c9cc-2e6f-55df-9925-410a450fdd1f.html",
      "source_name": "leadertelegram.com",
      "timestamp": "20260312T091500Z",
      "language": "English",
      "image": "https://bloximages.chicago2.vip.townnews.com/leadertelegram.com/content/tncms/custom/image/28cab52e-8460-11e8-a040-570b16e6f9e4.png",
      "lat": 32.43,
      "lng": 53.69
    },
    {
      "id": "gdelt-3163879910",
      "source": "gdelt",
      "category": "humanitarian",
      "title": "Were Ready for Long War that Will Destroy World Economy – Iran - Latest News In Nigeria , Nigeria News Today , Your Online Nigerian Newspaper",
      "country": "Iran",
      "url": "https://www.nigerianeye.com/2026/03/were-ready-for-long-war-that-will.html",
      "source_name": "nigerianeye.com",
      "timestamp": "20260312T091500Z",
      "language": "English",
      "image": "",
      "lat": 32.43,
      "lng": 53.69
    },
    {
      "id": "gdelt-3803608727",
      "source": "gdelt",
      "category": "humanitarian",
      "title": "PRIMERA DENUNCIA POR ATAQUE A IRÁN| Primera denuncia contra Trump y Netanyahu ante la Corte Penal Internacional por crímenes de guerra en el ataque contra Irán",
      "country": "",
      "url": "https://www.laprovincia.es/espana/2026/03/12/primera-denuncia-trump-netanyahu-corte-penal-internacional-ataque-iran-127858576.html",
      "source_name": "laprovincia.es",
      "timestamp": "20260312T091500Z",
      "language": "Spanish",
      "image": "https://estaticos-cdn.prensaiberica.es/clip/1714085c-8855-49d2-bc46-470461b39f2f_16-9-discover-aspect-ratio_default_0_x1200y533.jpg",
      "lat": null,
      "lng": null
    },
    {
      "id": "gdelt-2177103049",
      "source": "gdelt",
      "category": "humanitarian",
      "title": "Damage to historical sites in Iran raises alarm about war impact on protected places",
      "country": "Iran",
      "url": "https://mynorthwest.com/national/damage-to-historical-sites-in-iran-raises-alarm-about-wars-impact-on-protected-places/4215739",
      "source_name": "mynorthwest.com",
      "timestamp": "20260312T091500Z",
      "language": "English",
      "image": "",
      "lat": 32.43,
      "lng": 53.69
    },
    {
      "id": "gdelt-3989630541",
      "source": "gdelt",
      "category": "humanitarian",
      "title": "War damages historical sites in Iran",
      "country": "Iran",
      "url": "https://www.wsbradio.com/news/world/damage-historical/AUNFTIQBIQ4Z7H3J746QVCB22I/",
      "source_name": "wsbradio.com",
      "timestamp": "20260312T091500Z",
      "language": "English",
      "image": "https://www.wsbradio.com/resizer/_wglPira4yltTNLCSbmfhPQal7M=/arc-anglerfish-arc2-prod-cmg/public/W2TLZM5UKVHE3GH37MPPI76TS4.jpeg",
      "lat": 32.43,
      "lng": 53.69
    },
    {
      "id": "gdelt-2927063154",
      "source": "gdelt",
      "category": "humanitarian",
      "title": "US - und NATO - Militärbasis in Ramstein schließen",
      "country": "",
      "url": "https://www.nachdenkseiten.de/?p=147557",
      "source_name": "nachdenkseiten.de",
      "timestamp": "20260312T091500Z",
      "language": "German",
      "image": "https://www.nachdenkseiten.de/wp-content/uploads/2026/03/260312_dagdelen.jpg",
      "lat": null,
      "lng": null
    },
    {
      "id": "gdelt-2964462524",
      "source": "gdelt",
      "category": "humanitarian",
      "title": "Attacco alla base italiana di Erbil | nessun ferito tra i militari",
      "country": "",
      "url": "https://www.zazoom.it/2026-03-12/attacco-alla-base-italiana-di-erbil-nessun-ferito-tra-i-militari/18818066/",
      "source_name": "zazoom.it",
      "timestamp": "20260312T091500Z",
      "language": "Italian",
      "image": "https://361magazine.com/wp-content/uploads/2026/03/Libano-1773269021073.jpg-missile_su_base_italiana_a_erbil__militari_salvi__attacco_congiunto_iran_hezbollah_contro_israele_e_tensioni_nel_golfo.jpg",
      "lat": null,
      "lng": null
    },
    {
      "id": "gdelt-4201786518",
      "source": "gdelt",
      "category": "humanitarian",
      "title": "Россия направит в Иран 13 тонн медикаментов",
      "country": "",
      "url": "https://news.mail.ru/society/70127010/",
      "source_name": "news.mail.ru",
      "timestamp": "20260312T091500Z",
      "language": "Russian",
      "image": "https://resizer.mail.ru/p/cae3dd52-03d1-5e8d-89ab-35c8615397c7/AQAGoLzd1EZIw5ae88mH0sKsLb43sHf3CRzxkqDB3vvOalKUMNjPfNtRgV7Qb_gzetj2uz7GSj6nRIXG4XMksJLPiMY.jpg",
      "lat": null,
      "lng": null
    },
    {
      "id": "gdelt-1869562002",
      "source": "gdelt",
      "category": "humanitarian",
      "title": "BRET STEPHENS : What next in the Iran War ? | The Arkansas Democrat - Gazette",
      "country": "Iran",
      "url": "https://www.arkansasonline.com/news/2026/mar/12/bret-stephens-whats-next-in-the-iran-war/",
      "source_name": "arkansasonline.com",
      "timestamp": "20260312T091500Z",
      "language": "English",
      "image": "https://wehco.media.clients.ellingtoncms.com/static-4/teaser_images/www.arkansasonline.com_default.jpg",
      "lat": 32.43,
      "lng": 53.69
    },
    {
      "id": "gdelt-1093973393",
      "source": "gdelt",
      "category": "humanitarian",
      "title": "Bölgede iç savaþ ! Türkiye dahil 3 ülke ayný görte birleþti",
      "country": "",
      "url": "https://www.aksam.com.tr/dunya/bolgede-ic-savas-turkiye-dahil-3-ulke-ayni-goruste-birlesti/haber-1650260",
      "source_name": "aksam.com.tr",
      "timestamp": "20260312T091500Z",
      "language": "Turkish",
      "image": "https://img3.aksam.com.tr/imgsdisk/2026/03/12/t25_bolgede-ic-savas-turkiye--749.jpg",
      "lat": null,
      "lng": null
    },
    {
      "id": "gdelt-1731609210",
      "source": "gdelt",
      "category": "protest",
      "title": "列国鉴丨记者观察 ： 伊朗战事招致多重压力 特朗普政府或寻机退出 - 新华网",
      "country": "",
      "url": "https://www.news.cn/world/20260312/73b47d0dddff4a6fa866bd4e3a9689dd/c.html",
      "source_name": "news.cn",
      "timestamp": "20260312T090000Z",
      "language": "Chinese",
      "image": "",
      "lat": null,
      "lng": null
    },
    {
      "id": "gdelt-2940615510",
      "source": "gdelt",
      "category": "protest",
      "title": "На данашњи дан рођени војвода Степан Степа Степановић ( 1856 ); Владислав Петковић Дис ( 1880 ) и Кемал Ататурк ( 1881 ); 1935 . умро Михаило Пупин , 2003 . у атентату убијен Зоран Ђинђић",
      "country": "",
      "url": "http://www.nspm.rs/hronika/na-danasnji-dan-rodjeni-vojvoda-stepan-stepa-stepanovic-1856-vladislav-petkovic-dis-1880-i-kemal-ataturk-1881-1935.-umro-mihailo-pupin-2003.-u-atentatu-ubijen-zoran-djindjic.html",
      "source_name": "nspm.rs",
      "timestamp": "20260312T090000Z",
      "language": "Serbian",
      "image": "",
      "lat": null,
      "lng": null
    },
    {
      "id": "gdelt-1248405593",
      "source": "gdelt",
      "category": "protest",
      "title": "IN AGGIORNAMENTO . Intelligence united states : Governo iraniano non è a rischio collasso . Iraq , colpita base italiana , nessun ferito",
      "country": "Iraq",
      "url": "https://www.lantidiplomatico.it/dettnews-in_aggiornamento_intelligence_usa_governo_iraniano_non__a_rischio_collasso_iraq_colpita_base_italiana_nessun_ferito/45289_65555/",
      "source_name": "lantidiplomatico.it",
      "timestamp": "20260312T090000Z",
      "language": "Italian",
      "image": "",
      "lat": 33.22,
      "lng": 43.68
    },
    {
      "id": "gdelt-3048353553",
      "source": "gdelt",
      "category": "protest",
      "title": "Íránskému režimu zatím kolaps nehrozí , upozorňují rozvědky united states | Svět",
      "country": "",
      "url": "https://www.lidovky.cz/svet/iranskemu-rezimu-zatim-kolaps-nehrozi-upozornuji-americke-rozvedky.A260312_090205_ln_zahranici_lvot",
      "source_name": "lidovky.cz",
      "timestamp": "20260312T090000Z",
      "language": "Czech",
      "image": "https://1gr.cz/fotky/idnes/26/032/cl8/DTT980bd6107d_235849baaf60ef909344f910.jpg",
      "lat": null,
      "lng": null
    },
    {
      "id": "gdelt-3285885933",
      "source": "gdelt",
      "category": "protest",
      "title": "Azionario europeo in rosso con timori di shock petrolifero , a Milano corre Leonardo col piano",
      "country": "",
      "url": "https://finanza.lastampa.it/News/2026/03/12/azionario-europeo-in-rosso-con-timori-di-shock-petrolifero-a-milano-corre-leonardo-col-piano/NTFfMjAyNi0wMy0xMl9UTEI",
      "source_name": "finanza.lastampa.it",
      "timestamp": "20260312T090000Z",
      "language": "Italian",
      "image": "https://images.teleborsa.it/t/stabile/bc551d75-7457-40ce-8802-7cd8cce69488.t.W600.H340.M4.jpg",
      "lat": null,
      "lng": null
    },
    {
      "id": "gdelt-1854263952",
      "source": "gdelt",
      "category": "protest",
      "title": "Iran Ajukan 3 Syarat Akhiri Perang dengan AS dan Israel , Apa Saja ? ",
      "country": "Israel",
      "url": "https://www.kompas.com/tren/read/2026/03/12/143000465/iran-ajukan-3-syarat-akhiri-perang-dengan-as-dan-israel-apa-saja-",
      "source_name": "kompas.com",
      "timestamp": "20260312T090000Z",
      "language": "Indonesian",
      "image": "https://asset.kompas.com/crops/UdgTbtzNECHj6CxBvB6pHBq2cmg=/0x0:2000x1333/1200x675/filters:watermark(data/photo/2026/01/30/697c818d0ca91.png,0,-0,1)/data/photo/2026/03/07/69abedd2e366b.jpg",
      "lat": 31.05,
      "lng": 34.85
    },
    {
      "id": "gdelt-456262618",
      "source": "gdelt",
      "category": "protest",
      "title": "The Latest : Key oil price spikes over $100 as Iranian attacks hit shipping",
      "country": "Iran",
      "url": "https://www.mankatofreepress.com/news/state_national_news/the-latest-key-oil-price-spikes-over-100-as-iranian-attacks-hit-shipping/article_7099b763-396c-5476-952c-baea6792f4ab.html",
      "source_name": "mankatofreepress.com",
      "timestamp": "20260312T090000Z",
      "language": "English",
      "image": "https://bloximages.chicago2.vip.townnews.com/mankatofreepress.com/content/tncms/assets/v3/editorial/3/9c/39c32032-34a4-5223-a436-150a9ca6e663/69b17b312361b.image.jpg?crop=1764%2C926%2C0%2C124",
      "lat": 32.43,
      "lng": 53.69
    },
    {
      "id": "gdelt-4124342974",
      "source": "gdelt",
      "category": "protest",
      "title": "Azionario europeo in rosso con timori di shock petrolifero , a Milano corre Leonardo col piano",
      "country": "",
      "url": "https://www.teleborsa.it/News/2026/03/12/azionario-europeo-in-rosso-con-timori-di-shock-petrolifero-a-milano-corre-leonardo-col-piano-51.html",
      "source_name": "teleborsa.it",
      "timestamp": "20260312T090000Z",
      "language": "Italian",
      "image": "https://images.teleborsa.it/t/stabile/bc551d75-7457-40ce-8802-7cd8cce69488.t.W600.H340.M4.jpg",
      "lat": null,
      "lng": null
    },
    {
      "id": "gdelt-2321137799",
      "source": "gdelt",
      "category": "protest",
      "title": "Southeast Asia shuts offices , limits travel as oil crisis deepens",
      "country": "",
      "url": "https://www.aljazeera.com/news/2026/3/12/southeast-asia-shuts-offices-limits-travel-as-oil-crisis-deepens",
      "source_name": "aljazeera.com",
      "timestamp": "20260312T090000Z",
      "language": "English",
      "image": "https://www.aljazeera.com/wp-content/uploads/2026/03/2026-03-09T071945Z_8749907_RC2R0KAIGFRM_RTRMADP_3_IRAN-CRISIS-ENERGY-PHILIPPINES-1773297088_310258-1773302088.jpg",
      "lat": null,
      "lng": null
    },
    {
      "id": "gdelt-4199834140",
      "source": "gdelt",
      "category": "protest",
      "title": "Κλείνει ο σταθμός του μετρό « Σύνταγμα » στις 17 : 30 με εντολή της ΕΛ . ΑΣ . ",
      "country": "",
      "url": "https://www.news.gr/ellada/article/4095562/klini-o-stathmos-tou-metro-sintagma-stis-1730-me-entoli-tis-el-as.html",
      "source_name": "news.gr",
      "timestamp": "20260312T090000Z",
      "language": "Greek",
      "image": "https://www.news.gr/wp-content/uploads/images/2024/10/27/56/5684558.jpg",
      "lat": null,
      "lng": null
    },
    {
      "id": "gdelt-757083",
      "source": "gdelt",
      "category": "protest",
      "title": "Queensland  from the river to the sea  laws likened to Bjelke - Petersen era anti - protest regime | Queensland",
      "country": "",
      "url": "https://www.theguardian.com/australia-news/2026/mar/12/queensland-from-the-river-to-the-sea-pro-palestine-protest-slogan-laws-likened-to-bjelke-petersen-era-ntwnfb",
      "source_name": "theguardian.com",
      "timestamp": "20260312T090000Z",
      "language": "English",
      "image": "https://i.guim.co.uk/img/media/dade423b565ac8d6fd3372d27b23bbd143e9fad2/710_0_6455_5164/master/6455.jpg?&quality=85&auto=format&fit=crop&precrop=40:21,offset-x50,offset-y0&overlay-align=bottom%2Cleft&overlay-width=100p&overlay-base64=L2ltZy9zdGF0aWMvb3ZlcmxheXMvdGctZGVmYXVsdC5wbmc&enable=upscale&s=a6a72d29b8f561b2a5816a20c5e72bcb",
      "lat": null,
      "lng": null
    },
    {
      "id": "gdelt-3525547303",
      "source": "gdelt",
      "category": "protest",
      "title": "The Latest : Key oil price spikes over $100 as Iranian attacks hit shipping",
      "country": "Iran",
      "url": "https://www.ksat.com/news/2026/03/12/the-latest-key-oil-price-spikes-over-100-as-iranian-attacks-hit-shipping/",
      "source_name": "ksat.com",
      "timestamp": "20260312T090000Z",
      "language": "English",
      "image": "https://res.cloudinary.com/graham-media-group/image/upload/f_auto/q_auto/c_thumb,w_700/v1/media/gmg/JLVB3PQWLVDDDNCBS7TV64RTPA.jpg?_a=DATAg1fkZAA0",
      "lat": 32.43,
      "lng": 53.69
    },
    {
      "id": "gdelt-1954787570",
      "source": "gdelt",
      "category": "protest",
      "title": "আল - আকসা মসজিদ বন্ধ করে দেয়ায় ৮ মুসলিম দেশের তীব্র নিন্দা",
      "country": "",
      "url": "https://dailyinqilab.com/international/news/873284",
      "source_name": "dailyinqilab.com",
      "timestamp": "20260312T090000Z",
      "language": "Bengali",
      "image": "",
      "lat": null,
      "lng": null
    },
    {
      "id": "gdelt-3980455373",
      "source": "gdelt",
      "category": "protest",
      "title": "Barzaniye yakın Kürt liderden dikkat çeken sözler :  Batı ile temas halindeyiz  ",
      "country": "",
      "url": "https://anlatilaninotesi.com.tr/20260312/barzaniye-yakin-kurt-liderden-dikkat-ceken-sozler-bati-ile-temas-halindeyiz-1104195894.html",
      "source_name": "anlatilaninotesi.com.tr",
      "timestamp": "20260312T090000Z",
      "language": "Turkish",
      "image": "https://cdn.img.anlatilaninotesi.com.tr/images/sharing/article/tur/1104195894.jpg",
      "lat": null,
      "lng": null
    },
    {
      "id": "gdelt-549696647",
      "source": "gdelt",
      "category": "protest",
      "title": "Πόλεμος στη Μέση Ανατολή : Δεν « πέφτει » το καθεστώς του Ιράν , λένε οι μυστικές υπηρεσίες των ΗΠΑ",
      "country": "",
      "url": "https://www.topontiki.gr/2026/03/12/polemos-sti-mesi-anatoli-den-pefti-to-kathestos-tou-iran-lene-i-mistikes-ipiresies-ton-ipa/",
      "source_name": "topontiki.gr",
      "timestamp": "20260312T090000Z",
      "language": "Greek",
      "image": "https://www.topontiki.gr/wp-content/uploads/2026/03/iran-123-new.jpg",
      "lat": null,
      "lng": null
    },
    {
      "id": "gdelt-2474309091",
      "source": "gdelt",
      "category": "protest",
      "title": "  Odsečete jednu glavu , izraste nova : Kako su vladari Irana stvorili sistem koji ih održava na vlasti :: BBC :: RTCG - Radio Televizija Crne Gore",
      "country": "Iran",
      "url": "https://rtcg.me/vijesti/bbc/822785/odsecete-jednu-glavu-izraste-nova-kako-su-vladari-irana-stvorili-sistem-koji-ih-odrzava-na-vlasti.html",
      "source_name": "rtcg.me",
      "timestamp": "20260312T090000Z",
      "language": "Serbian",
      "image": "https://rtcg.me/upload/media/2026/2/12/9/13/952/2459324/thumbs/5991038/thumb0.jpg",
      "lat": 32.43,
      "lng": 53.69
    },
    {
      "id": "gdelt-1872112014",
      "source": "gdelt",
      "category": "protest",
      "title": "Μετρό : Κλείνει στις 17 : 30 ο σταθμός « Σύνταγμα » λίγο πριν από την αντιπολεμική διαδήλωση",
      "country": "",
      "url": "https://www.in.gr/2026/03/12/greece/metro-kleinei-stis-1730-o-stathmos-syntagma-ligo-prin-apo-tin-antipolemiki-diadilosi/",
      "source_name": "in.gr",
      "timestamp": "20260312T090000Z",
      "language": "Greek",
      "image": "https://www.in.gr/wp-content/uploads/2026/03/EV_GK_140518_APERGIA_METRO8-620x350.jpg",
      "lat": null,
      "lng": null
    },
    {
      "id": "gdelt-376070696",
      "source": "gdelt",
      "category": "protest",
      "title": "穆杰塔巴为何能  子承父业  接任伊朗最高领袖 ？_ 中国网",
      "country": "",
      "url": "http://www.china.com.cn/opinion2020/2026-03/12/content_118378875.shtml",
      "source_name": "china.com.cn",
      "timestamp": "20260312T090000Z",
      "language": "Chinese",
      "image": "",
      "lat": null,
      "lng": null
    },
    {
      "id": "gdelt-4072443337",
      "source": "gdelt",
      "category": "humanitarian",
      "title": "Ислам - тудей : обзор новостей за 24 часа",
      "country": "",
      "url": "https://islam-today.ru/islam_v_mire/islam-tudej-dajdzest-novostej-za-24-cas12March2026/",
      "source_name": "islam-today.ru",
      "timestamp": "20260312T090000Z",
      "language": "Russian",
      "image": "https://islam-today.ru/files/news/part_15/158054/preview-440x301.jpg",
      "lat": null,
      "lng": null
    },
    {
      "id": "gdelt-649045242",
      "source": "gdelt",
      "category": "humanitarian",
      "title": "Bhilwara Textile Industry faces uncertainty amid Middle East crisis",
      "country": "",
      "url": "https://aninews.in/news/national/general-news/bhilwaras-textile-industry-faces-uncertainty-amid-middle-east-crisis20260312133355/",
      "source_name": "aninews.in",
      "timestamp": "20260312T090000Z",
      "language": "English",
      "image": "https://d3lzcn6mbbadaf.cloudfront.net/media/details/ANI-20260312075951.jpg",
      "lat": null,
      "lng": null
    },
    {
      "id": "gdelt-298255331",
      "source": "gdelt",
      "category": "humanitarian",
      "title": "PRIMERA DENUNCIA POR ATAQUE A IRÁN| Primera denuncia contra Trump y Netanyahu ante la Corte Penal Internacional por crímenes de guerra en el ataque contra Irán",
      "country": "",
      "url": "https://www.elperiodicodearagon.com/espana/2026/03/12/primera-denuncia-trump-netanyahu-corte-penal-internacional-ataque-iran-127858510.html",
      "source_name": "elperiodicodearagon.com",
      "timestamp": "20260312T090000Z",
      "language": "Spanish",
      "image": "https://estaticos-cdn.prensaiberica.es/clip/1714085c-8855-49d2-bc46-470461b39f2f_16-9-discover-aspect-ratio_default_0_x1200y533.jpg",
      "lat": null,
      "lng": null
    },
    {
      "id": "gdelt-2754794323",
      "source": "gdelt",
      "category": "humanitarian",
      "title": "Ideas & Opinions Hits & Misses : Miss to the  Welcome  sign on Highway 49",
      "country": "",
      "url": "https://www.theunion.com/news/community/ideas-opinions-hits-misses-miss-to-the-welcome-sign-on-highway-49/article_215300b6-a848-4050-b37a-719c942054e2.html",
      "source_name": "theunion.com",
      "timestamp": "20260312T090000Z",
      "language": "English",
      "image": "https://bloximages.chicago2.vip.townnews.com/theunion.com/content/tncms/custom/image/895f2392-650d-11ed-9099-fb46053bbb4c.png",
      "lat": null,
      "lng": null
    },
    {
      "id": "gdelt-3184355204",
      "source": "gdelt",
      "category": "humanitarian",
      "title": " « Проверка на вшивость »: США наложили вето в ООН на резолюцию России по Ближнему Востоку",
      "country": "",
      "url": "https://www.golosarmenii.am/%D0%BF%D1%80%D0%BE%D0%B2%D0%B5%D1%80%D0%BA%D0%B0-%D0%BD%D0%B0-%D0%B2%D1%88%D0%B8%D0%B2%D0%BE%D1%81%D1%82%D1%8C-%D1%81%D1%88%D0%B0-%D0%BD%D0%B0%D0%BB%D0%BE%D0%B6%D0%B8%D0%BB%D0%B8-%D0%B2%D0%B5/",
      "source_name": "golosarmenii.am",
      "timestamp": "20260312T090000Z",
      "language": "Russian",
      "image": "https://www.golosarmenii.am/wp-content/uploads/2026/03/91877890_0_160_3072_1888_1920x0_80_0_0_a3651cbfab7dd67d654545bc939f799f.jpg.webp",
      "lat": null,
      "lng": null
    },
    {
      "id": "gdelt-2969302559",
      "source": "gdelt",
      "category": "humanitarian",
      "title": "Реџеп Тајип Ердоган : Нетанјаху је највећа катастрофа за Јевреје од Холокауста",
      "country": "",
      "url": "http://www.nspm.rs/hronika/redzep-tajip-erdogan-netanjahu-je-najveca-katastrofa-za-jevreje-od-holokausta.html",
      "source_name": "nspm.rs",
      "timestamp": "20260312T090000Z",
      "language": "Serbian",
      "image": "",
      "lat": null,
      "lng": null
    },
    {
      "id": "gdelt-3913708370",
      "source": "gdelt",
      "category": "humanitarian",
      "title": "Не только нефть : мишенью ударов ближневосточной войны стала вода",
      "country": "",
      "url": "https://www.mk.ru/politics/2026/03/12/ne-tolko-neft-mishenyu-udarov-blizhnevostochnoy-voyny-stala-voda.html",
      "source_name": "mk.ru",
      "timestamp": "20260312T090000Z",
      "language": "Russian",
      "image": "https://static.mk.ru/upload/entities/2026/03/12/09/articles/facebookPicture/e0/4b/61/f4/3b875da198ef1d5118ccea2f5c77900a.jpg",
      "lat": null,
      "lng": null
    },
    {
      "id": "gdelt-3391204003",
      "source": "gdelt",
      "category": "humanitarian",
      "title": "US - Israeli strike hits industrial area near Tehran ; abandoned warehouse among targets struck",
      "country": "Tehran",
      "url": "http://www.australiannews.net/news/278917343/us-israeli-strike-hits-industrial-area-near-tehran-abandoned-warehouse-among-targets-struck",
      "source_name": "australiannews.net",
      "timestamp": "20260312T090000Z",
      "language": "English",
      "image": "https://image.chitra.live/api/v1/wps/f74ee3e/921f439e-58b7-46b3-a9ab-9f0c40f282b7/0/ANI-20260312061401-600x315.jpg",
      "lat": 35.69,
      "lng": 51.39
    },
    {
      "id": "gdelt-183293113",
      "source": "gdelt",
      "category": "humanitarian",
      "title": "Damage to historical sites in Iran raises alarm about war impact on protected places",
      "country": "Iran",
      "url": "https://www.therecord.com/news/world/damage-to-historical-sites-in-iran-raises-alarm-about-wars-impact-on-protected-places/article_02516b7a-ce8d-5697-9cce-7e0f4a9f37f3.html",
      "source_name": "therecord.com",
      "timestamp": "20260312T090000Z",
      "language": "English",
      "image": "https://bloximages.chicago2.vip.townnews.com/therecord.com/content/tncms/custom/image/23af3362-fbf7-11ed-9682-4fc0f10dbc1a.png",
      "lat": 32.43,
      "lng": 53.69
    },
    {
      "id": "gdelt-2166163368",
      "source": "gdelt",
      "category": "humanitarian",
      "title": "Liban : au moins sept morts dans une nouvelle attaque sur le centre de Beyrouth",
      "country": "",
      "url": "https://fr.le360.ma/monde/liban-au-moins-sept-morts-dans-une-nouvelle-attaque-sur-le-centre-de-beyrouth_GGB4YHSVZJD23KBSRMRGAIQHXE/",
      "source_name": "fr.le360.ma",
      "timestamp": "20260312T090000Z",
      "language": "French",
      "image": "https://fr.le360.ma/resizer/v2/A4SK44ZTU5DANOWPCHRMIK7FYY.jpg?auth=b1b042faf12ab743c98608036740fabfcfb8454450dc81e9729ddd26aa92ef63&smart=true",
      "lat": null,
      "lng": null
    },
    {
      "id": "gdelt-2770880834",
      "source": "gdelt",
      "category": "humanitarian",
      "title": "Tramp poziva na ustanak u Iranu , zanemarujući lekciju iz Iraka 1991 : BBC urednik :: BBC :: RTCG - Radio Televizija Crne Gore",
      "country": "Iran",
      "url": "https://rtcg.me/vijesti/bbc/822791/tramp-poziva-na-ustanak-u-iranu-zanemarujuci-lekciju-iz-iraka-1991-bbc-urednik.html",
      "source_name": "rtcg.me",
      "timestamp": "20260312T090000Z",
      "language": "Serbian",
      "image": "https://rtcg.me/upload/media/2026/2/12/9/43/0/2459318/thumbs/5990996/thumb0.jpg",
      "lat": 32.43,
      "lng": 53.69
    },
    {
      "id": "gdelt-1172817411",
      "source": "gdelt",
      "category": "humanitarian",
      "title": "700 isimden İran bildirisi",
      "country": "Iran",
      "url": "https://www.odatv.com/dunya/700-isimden-iran-bildirisi-120139186",
      "source_name": "odatv.com",
      "timestamp": "20260312T090000Z",
      "language": "Turkish",
      "image": "https://img.odatv.com/rcman/Cw1280h720q95gc/storage/files/images/2026/03/12/700-isimden-iran-bildirisi-opmv.jpg",
      "lat": 32.43,
      "lng": 53.69
    },
    {
      "id": "gdelt-3340728010",
      "source": "gdelt",
      "category": "humanitarian",
      "title": "SON DAKİKA HABERLER : ABD - İsrail - İran savaşının 13 . gününde Orta Doğu ateş çemberi ! ",
      "country": "Iran",
      "url": "https://www.milliyet.com.tr/dunya/live-son-dakika-abd-israil-iran-savasinin-13-gununde-orta-dogu-ates-cemberi-tahran-tel-avive-kamikaze-dron-yagdirdi-israil-istihbarati-hedefte-7552984",
      "source_name": "milliyet.com.tr",
      "timestamp": "20260312T090000Z",
      "language": "Turkish",
      "image": "https://image.milimaj.com/i/milliyet/75/0x0/69b23dc92f3815012604ebec.jpg",
      "lat": 32.43,
      "lng": 53.69
    },
    {
      "id": "gdelt-167802183",
      "source": "gdelt",
      "category": "humanitarian",
      "title": "US , Israel using nuclear pretext in quest for regime change : Iran",
      "country": "Israel",
      "url": "https://www.capitalfm.co.ke/news/2026/03/us-israel-using-nuclear-pretext-in-quest-for-regime-change-iranian-envoy-in-nairobi/",
      "source_name": "capitalfm.co.ke",
      "timestamp": "20260312T090000Z",
      "language": "English",
      "image": "https://www.capitalfm.co.ke/news/files/2026/03/ALI-GHOLAMPOUR-1024x576.png",
      "lat": 31.05,
      "lng": 34.85
    },
    {
      "id": "gdelt-1143096231",
      "source": "gdelt",
      "category": "humanitarian",
      "title": "إيران تكشف تفاصيل أول هجوم منسق مع حزب الله على إسرائيل منذ اندلاع الحرب",
      "country": "",
      "url": "https://www.shorouknews.com/news/view.aspx?cdate=12032026&id=dec8caea-c460-419c-ac64-a875cc869c94",
      "source_name": "shorouknews.com",
      "timestamp": "20260312T090000Z",
      "language": "Arabic",
      "image": "https://www.shorouknews.com/uploadedimages/Other/original/4%D9%8154%D9%82%D9%8154%D9%81%D8%A85%D9%82%D8%A8%D9%8A%D9%81%D9%8255%D8%AB4.JPG",
      "lat": null,
      "lng": null
    },
    {
      "id": "gdelt-2962890472",
      "source": "gdelt",
      "category": "humanitarian",
      "title": "US - Israeli strike hits industrial area near Tehran ; abandoned warehouse among targets struck",
      "country": "Tehran",
      "url": "http://www.heraldglobe.com/news/278917343/us-israeli-strike-hits-industrial-area-near-tehran-abandoned-warehouse-among-targets-struck",
      "source_name": "heraldglobe.com",
      "timestamp": "20260312T090000Z",
      "language": "English",
      "image": "https://image.chitra.live/api/v1/wps/f74ee3e/921f439e-58b7-46b3-a9ab-9f0c40f282b7/0/ANI-20260312061401-600x315.jpg",
      "lat": 35.69,
      "lng": 51.39
    },
    {
      "id": "gdelt-4013784863",
      "source": "gdelt",
      "category": "humanitarian",
      "title": "Why India joined 130 nations at the UN to condemn Iran  egregious  attacks on Gulf allies",
      "country": "Iran",
      "url": "https://indianexpress.com/article/india/india-unsc-resolution-iranian-strikes-gulf-countries-10578125/",
      "source_name": "indianexpress.com",
      "timestamp": "20260312T090000Z",
      "language": "English",
      "image": "https://images.indianexpress.com/2026/03/dubai-1600.jpg",
      "lat": 32.43,
      "lng": 53.69
    },
    {
      "id": "gdelt-2416135730",
      "source": "gdelt",
      "category": "humanitarian",
      "title": "Ataques israelenses deixam mortos perto de Beirute e intensificam guerra contra o Líbano",
      "country": "Israel",
      "url": "https://www.brasil247.com:443/mundo/ataques-israelenses-deixam-mortos-perto-de-beirute-e-intensificam-guerra-contra-o-libano",
      "source_name": "brasil247.com",
      "timestamp": "20260312T090000Z",
      "language": "Portuguese",
      "image": "https://cdn.brasil247.com/pb-b247gcp/swp/jtjeq9/media/2026030305030_67a27ad2bec0e57898667acf6a5182963f53ed778c388b58768aabb51985a482.jpg",
      "lat": 31.05,
      "lng": 34.85
    },
    {
      "id": "gdelt-2032235411",
      "source": "gdelt",
      "category": "humanitarian",
      "title": "伊朗公布美导弹袭击学校  铁证 ： 导弹残片上  美国制造  清晰可见 ， 伊方警告将反击 _ 军事频道 _ 中华网",
      "country": "",
      "url": "https://military.china.com/news/13004177/20260312/49316616.html",
      "source_name": "military.china.com",
      "timestamp": "20260312T090000Z",
      "language": "Chinese",
      "image": "",
      "lat": null,
      "lng": null
    },
    {
      "id": "gdelt-2000135174",
      "source": "gdelt",
      "category": "humanitarian",
      "title": "  Unjust and unlawful : Iran rejects UNSC resolution , warns of  lasting stain  on Council record",
      "country": "Iran",
      "url": "https://aninews.in/news/world/us/unjust-and-unlawful-iran-rejects-unsc-resolution-warns-of-lasting-stain-on-councils-record20260312132855/",
      "source_name": "aninews.in",
      "timestamp": "20260312T090000Z",
      "language": "English",
      "image": "https://d3lzcn6mbbadaf.cloudfront.net/media/details/ANI-20260312075841.jpg",
      "lat": 32.43,
      "lng": 53.69
    },
    {
      "id": "gdelt-2610174306",
      "source": "gdelt",
      "category": "humanitarian",
      "title": "Damage to historical sites in Iran raises alarm about war impact on protected places",
      "country": "Iran",
      "url": "https://isp.netscape.com/news/world/story/0001/20260312/bff566d6bc1fb7167614b43690277414",
      "source_name": "isp.netscape.com",
      "timestamp": "20260312T090000Z",
      "language": "English",
      "image": "",
      "lat": 32.43,
      "lng": 53.69
    },
    {
      "id": "gdelt-1612750063",
      "source": "gdelt",
      "category": "humanitarian",
      "title": "  Ýyi ki varsýn Türkiye ... Gazzeli çocuklardan yürekleri ýsýtan teþekkür",
      "country": "",
      "url": "https://www.aksam.com.tr/guncel/iyi-ki-varsin-turkiye-gazzeli-cocuklardan-yurekleri-isitan-tesekkur/haber-1650231",
      "source_name": "aksam.com.tr",
      "timestamp": "20260312T090000Z",
      "language": "Turkish",
      "image": "https://img3.aksam.com.tr/imgsdisk/2026/03/12/t25_iyi-ki-varsin-turkiye-gaz-496.jpg",
      "lat": null,
      "lng": null
    },
    {
      "id": "gdelt-1668418165",
      "source": "gdelt",
      "category": "humanitarian",
      "title": "Indonesia kutuk langkah Israel tutup Masjid Al - Aqsa pada Ramadhan",
      "country": "Israel",
      "url": "https://ramadhan.antaranews.com/berita/5469283/indonesia-kutuk-langkah-israel-tutup-masjid-al-aqsa-pada-ramadhan",
      "source_name": "ramadhan.antaranews.com",
      "timestamp": "20260312T090000Z",
      "language": "Indonesian",
      "image": "https://img.antaranews.com/cache/1200x800/2026/02/21/Jamaah.jpg",
      "lat": 31.05,
      "lng": 34.85
    },
    {
      "id": "gdelt-2596540864",
      "source": "gdelt",
      "category": "humanitarian",
      "title": "Passivitetens tid är öve – nu måste vi stötta folket i Iran",
      "country": "Iran",
      "url": "https://www.gp.se/debatt/nu-finns-en-historisk-chans-for-regimskifte-i-iran-tar-vi-den-inte-sviker-vi-folket.bc488e5c-8d3b-48a2-a7cd-ce7ed02a135f",
      "source_name": "gp.se",
      "timestamp": "20260312T090000Z",
      "language": "Swedish",
      "image": "https://www.gp.se/images/og/bc488e5c-8d3b-48a2-a7cd-ce7ed02a135f/images/2bAiLfBKen6TBAL9oCm62uiw-ZBo-WIDE.jpg?&quality=75",
      "lat": 32.43,
      "lng": 53.69
    },
    {
      "id": "gdelt-2469392210",
      "source": "gdelt",
      "category": "protest",
      "title": "ഒമാനെ ആക്രമിച്ചത് തങ്ങളല്ലെന്ന് ഇറാൻ ;  യു . എസ് - ഇസ്രായേൽ സഖ്യം നടത്തിയ ആക്രമണം , സംശയാസ്പദം  | Iran denies any role in oman strikes and may have been an Israeli false ‑ flag operation",
      "country": "Iran",
      "url": "https://www.madhyamam.com/world/iran-denies-any-role-in-oman-strikes-and-may-have-been-an-israeli-falseflag-operation-1502340",
      "source_name": "madhyamam.com",
      "timestamp": "20260312T084500Z",
      "language": "Malayalam",
      "image": "https://www.madhyamam.com/h-upload/2026/03/12/2811480-oman-strike.jpg",
      "lat": 32.43,
      "lng": 53.69
    },
    {
      "id": "gdelt-2535556797",
      "source": "gdelt",
      "category": "humanitarian",
      "title": "Beirut es converteix en un camp de refugiats gegant :  Som gent que vol viure  ",
      "country": "Beirut",
      "url": "https://www.ara.cat/internacional/proxim-orient/beirut-converteix-camp-refugiats-gegant-gent-vol-viure_130_5674078.html",
      "source_name": "ara.cat",
      "timestamp": "20260312T084500Z",
      "language": "Catalan",
      "image": "https://static1.ara.cat/clip/b640afff-2dd3-4bed-b90b-124c9964544a_facebook-aspect-ratio_default_0.jpg",
      "lat": 33.89,
      "lng": 35.5
    },
    {
      "id": "gdelt-119646162",
      "source": "gdelt",
      "category": "protest",
      "title": "Addio alla libreria Hoepli ? Milano si ribella | Diventi bottega storica per salvarsi",
      "country": "",
      "url": "https://www.zazoom.it/2026-03-12/addio-alla-libreria-hoepli-milano-si-ribella-diventi-bottega-storica-per-salvarsi/18817399/",
      "source_name": "zazoom.it",
      "timestamp": "20260312T083000Z",
      "language": "Italian",
      "image": "https://www.zazoom.it/news.jpg",
      "lat": null,
      "lng": null
    },
    {
      "id": "gdelt-3630373373",
      "source": "gdelt",
      "category": "protest",
      "title": "Тайское судно атаковано в Ормузском проливе , трое моряков заблокированы | MigNews - Новости Израиля и Мира на русском языке",
      "country": "",
      "url": "http://mignews.com/news/disasters/tajskoe-sudno-atakovano-v-ormuzskom-prolive-troe-moryakov-zablokirovany.html",
      "source_name": "mignews.com",
      "timestamp": "20260312T083000Z",
      "language": "Russian",
      "image": "https://mignews.com/media/cache/8b/d8/8bd87e2476d0540941799723b14597d9.jpg",
      "lat": null,
      "lng": null
    },
    {
      "id": "gdelt-2888851290",
      "source": "gdelt",
      "category": "protest",
      "title": "Íránskému režimu podle amerických rozvědek zatím nehrozí kolaps , píše Reuters",
      "country": "",
      "url": "https://www.ceskenoviny.cz/zpravy/iranskemu-rezimu-podle-americkych-rozvedek-zatim-nehrozi-kolaps-pise-reuters/2798243",
      "source_name": "ceskenoviny.cz",
      "timestamp": "20260312T083000Z",
      "language": "Czech",
      "image": "https://i3.cn.cz/16/1773215768_P2026031102700.jpg",
      "lat": null,
      "lng": null
    },
    {
      "id": "gdelt-1335745917",
      "source": "gdelt",
      "category": "protest",
      "title": "Khamenei , Trump , Netanyahu",
      "country": "",
      "url": "https://mediaindonesia.com/opini/869639/khamenei-trump-netanyahu",
      "source_name": "mediaindonesia.com",
      "timestamp": "20260312T083000Z",
      "language": "Indonesian",
      "image": "https://asset.mediaindonesia.com/news/2026/03/12/1773301178_8c768152ba88577c7ca8.jpeg",
      "lat": null,
      "lng": null
    },
    {
      "id": "gdelt-976239826",
      "source": "gdelt",
      "category": "protest",
      "title": "LIVE – Πόλεμος φθοράς από το Ιράν με επιθέσεις σε δεξαμενόπλοια – Εντυπωσιακά βίντεο από τη διάσωση των ναυτικών – Όλες οι πολεμικές εξελίξεις",
      "country": "",
      "url": "https://newpost.gr/eidiseis/live-polemos-fthoras-apo-to-iran-me-epitheseis-se-dexamenoploia-entyposiaka-vinteo-apo-ti-diasosi-ton-naytikon-oles-oi-polemikes-exelixeis/",
      "source_name": "newpost.gr",
      "timestamp": "20260312T083000Z",
      "language": "Greek",
      "image": "https://newpost.gr/wp-content/uploads/2026/03/31575693.jpg",
      "lat": null,
      "lng": null
    },
    {
      "id": "gdelt-990980388",
      "source": "gdelt",
      "category": "protest",
      "title": "Nach Trumps Freifahrt - Schein : Tod auf See - Öltanker steht in Flammen",
      "country": "",
      "url": "https://www.finanznachrichten.de/nachrichten-2026-03/67923042-nach-trumps-freifahrt-schein-tod-auf-see-oeltanker-steht-in-flammen-124.htm",
      "source_name": "finanznachrichten.de",
      "timestamp": "20260312T081500Z",
      "language": "German",
      "image": "https://www.finanznachrichten.de/content/g/fb.png",
      "lat": null,
      "lng": null
    },
    {
      "id": "gdelt-2635815022",
      "source": "gdelt",
      "category": "protest",
      "title": "وزير الدفاع الإندونيسي : نشر قوات بغزة يعتمد على  مجلس السلام  ",
      "country": "",
      "url": "https://www.aljazeera.net/news/2026/3/12/%D9%88%D8%B2%D9%8A%D8%B1-%D8%A7%D9%84%D8%AF%D9%81%D8%A7%D8%B9-%D8%A7%D9%84%D8%A5%D9%86%D8%AF%D9%88%D9%86%D9%8A%D8%B3%D9%8A-%D9%86%D8%B4%D8%B1-%D9%82%D9%88%D8%A7%D8%AA-%D8%A8%D8%BA%D8%B2%D8%A9",
      "source_name": "aljazeera.net",
      "timestamp": "20260312T081500Z",
      "language": "Arabic",
      "image": "https://www.aljazeera.net/wp-content/uploads/2026/03/indo3-1773295919.jpg",
      "lat": null,
      "lng": null
    },
    {
      "id": "gdelt-1001047807",
      "source": "gdelt",
      "category": "humanitarian",
      "title": "La guerra se focaliza en Ormuz",
      "country": "",
      "url": "https://www.lavanguardia.com/internacional/20260312/11487484/guerra-focaliza-ormuz.html",
      "source_name": "lavanguardia.com",
      "timestamp": "20260312T081500Z",
      "language": "Spanish",
      "image": "https://www.lavanguardia.com/files/og_thumbnail/files/fp/uploads/2026/03/11/69b12b25a3cc1.r_d.359-154-0.jpeg",
      "lat": null,
      "lng": null
    },
    {
      "id": "gdelt-2878155256",
      "source": "gdelt",
      "category": "humanitarian",
      "title": "Damage to historical sites in Iran raises alarm about war impact on protected places",
      "country": "Iran",
      "url": "https://www.wboc.com/news/international/damage-to-historical-sites-in-iran-raises-alarm-about-wars-impact-on-protected-places/article_e75b5336-a31a-5ffd-aabb-bc74b243e175.html",
      "source_name": "wboc.com",
      "timestamp": "20260312T081500Z",
      "language": "English",
      "image": "https://bloximages.newyork1.vip.townnews.com/wboc.com/content/tncms/custom/image/03429210-c538-11eb-8535-3f39d79b272b.png",
      "lat": 32.43,
      "lng": 53.69
    },
    {
      "id": "gdelt-1391503051",
      "source": "gdelt",
      "category": "humanitarian",
      "title": "Jane Houng on her dedication to women safety after the murder of her daughter",
      "country": "",
      "url": "https://www.scmp.com/postmag/passions/article/3345711/jane-houng-her-dedication-womens-safety-after-murder-her-daughter",
      "source_name": "scmp.com",
      "timestamp": "20260312T081500Z",
      "language": "English",
      "image": "https://cdn.i-scmp.com/sites/default/files/styles/og_postmag/public/d8/images/canvas/2026/03/08/cf1e0f6a-8ea5-44c0-b653-e1b24b33efca_0227f696.jpg?itok=mTmvv9IT&v=1772983505",
      "lat": null,
      "lng": null
    },
    {
      "id": "gdelt-2880149012",
      "source": "gdelt",
      "category": "humanitarian",
      "title": "Middle East Update : Shipping Attacks , Oil Surge , Crisis",
      "country": "",
      "url": "https://www.miragenews.com/middle-east-update-shipping-attacks-oil-surge-1635830/",
      "source_name": "miragenews.com",
      "timestamp": "20260312T081500Z",
      "language": "English",
      "image": "",
      "lat": null,
      "lng": null
    },
    {
      "id": "gdelt-2334162606",
      "source": "gdelt",
      "category": "humanitarian",
      "title": "TDV , zekat bağışlarını yurt içi ve yurt dışındaki ihtiyaç sahiplerine ulaştırıyor",
      "country": "",
      "url": "https://www.haberler.com/guncel/turkiye-diyanet-vakfi-ndan-zekat-kampanyasi-19649533-haberi/",
      "source_name": "haberler.com",
      "timestamp": "20260312T081500Z",
      "language": "Turkish",
      "image": "",
      "lat": null,
      "lng": null
    },
    {
      "id": "gdelt-434648776",
      "source": "gdelt",
      "category": "humanitarian",
      "title": "İşgal rejimi bölgesel savaşı fırsata çeviriyor",
      "country": "",
      "url": "https://www.haksozhaber.net/isgal-rejimi-bolgesel-savasi-firsata-ceviriyor-201239h.htm",
      "source_name": "haksozhaber.net",
      "timestamp": "20260312T081500Z",
      "language": "Turkish",
      "image": "https://www.haksozhaber.net/d/news/203953.jpg",
      "lat": null,
      "lng": null
    },
    {
      "id": "gdelt-488067284",
      "source": "gdelt",
      "category": "protest",
      "title": "After Israeli intelligence infiltration , Iran deploys elite NOPO force to guard new leader Mojtaba Khamenei",
      "country": "Iran",
      "url": "https://economictimes.indiatimes.com/news/defence/after-israeli-intelligence-infiltration-iran-deploys-elite-nopo-force-to-guard-new-leader-mojtaba-khamenei/articleshow/129496526.cms",
      "source_name": "economictimes.indiatimes.com",
      "timestamp": "20260312T080000Z",
      "language": "English",
      "image": "https://img.etimg.com/thumb/msid-129497481,width-1200,height-630,imgsize-2136533,overlay-etdefence/articleshow.jpg",
      "lat": 32.43,
      "lng": 53.69
    },
    {
      "id": "gdelt-1685316265",
      "source": "gdelt",
      "category": "protest",
      "title": "Iran tells world to get ready for oil at $200 a barrel as it fires on merchant ships",
      "country": "Iran",
      "url": "https://www.aol.com/articles/iran-tells-world-ready-oil-003710768.html",
      "source_name": "aol.com",
      "timestamp": "20260312T080000Z",
      "language": "English",
      "image": "https://s.yimg.com/os/en/reuters.ca/b0a410e61cd7e9e2186f243a850f1b31",
      "lat": 32.43,
      "lng": 53.69
    },
    {
      "id": "gdelt-3247760774",
      "source": "gdelt",
      "category": "protest",
      "title": "CSG reconsiders vetoed Divest for Humanity Act",
      "country": "",
      "url": "https://www.michigandaily.com/news/student-government/csg-reconsiders-vetoed-divest-for-humanity-act-hears-from-umich-students-and-community/",
      "source_name": "michigandaily.com",
      "timestamp": "20260312T080000Z",
      "language": "English",
      "image": "https://www.michigandaily.com/wp-content/uploads/2026/03/rdx.NEW_.CSG_.02.24.26.06.jpg",
      "lat": null,
      "lng": null
    },
    {
      "id": "gdelt-3023240568",
      "source": "gdelt",
      "category": "protest",
      "title": "  Odsečete jednu glavu , izraste nova : Kako su vladari Irana stvorili sistem koji ih održava na vlasti",
      "country": "Iran",
      "url": "https://www.nin.rs/bbc/vesti/106813/odsecete-jednu-glavu-izraste-nova-kako-su-vladari-irana-stvorili-sistem-koji-ih-odrzava-na-vlasti",
      "source_name": "nin.rs",
      "timestamp": "20260312T080000Z",
      "language": "Serbian",
      "image": "https://www.nin.rs/data/images/2026-03-12/104952_01488100-1c7b-11f1-a7bf-efb6e72f87e6_og.jpg",
      "lat": 32.43,
      "lng": 53.69
    },
    {
      "id": "gdelt-1500144516",
      "source": "gdelt",
      "category": "protest",
      "title": "The Latest : Key oil price spikes over $100 as Iranian attacks hit shipping",
      "country": "Iran",
      "url": "https://www.news4jax.com/news/2026/03/12/the-latest-key-oil-price-spikes-over-100-as-iranian-attacks-hit-shipping/",
      "source_name": "news4jax.com",
      "timestamp": "20260312T080000Z",
      "language": "English",
      "image": "https://res.cloudinary.com/graham-media-group/image/upload/f_auto/q_auto/c_thumb,w_700/v1/media/gmg/JLVB3PQWLVDDDNCBS7TV64RTPA.jpg?_a=DATAg1fkZAA0",
      "lat": 32.43,
      "lng": 53.69
    },
    {
      "id": "gdelt-2803708896",
      "source": "gdelt",
      "category": "protest",
      "title": "国际能源署释放史上最大规模石油储备 ， 伊朗警告 ： 油价要涨到每桶200美元",
      "country": "",
      "url": "https://news.ifeng.com/c/8rQzIV0i7T7",
      "source_name": "news.ifeng.com",
      "timestamp": "20260312T080000Z",
      "language": "Chinese",
      "image": "https://x0.ifengimg.com/ucms/2026_11/6276174D6ACE9BE6D92C9507C12CF65D7E9AB9DE_size373_w664_h373.png",
      "lat": null,
      "lng": null
    },
    {
      "id": "gdelt-1996633353",
      "source": "gdelt",
      "category": "protest",
      "title": "Activists march for International Working Women Day",
      "country": "",
      "url": "https://www.michigandaily.com/news/campus-life/activists-march-through-campus-in-celebration-of-international-working-womens-day/",
      "source_name": "michigandaily.com",
      "timestamp": "20260312T080000Z",
      "language": "English",
      "image": "https://www.michigandaily.com/wp-content/uploads/2026/03/lle.NEW_.InternationalWorkingWomensDayProtest.3.10.26.019.jpg",
      "lat": null,
      "lng": null
    },
    {
      "id": "gdelt-2407845872",
      "source": "gdelt",
      "category": "protest",
      "title": "Cum au subestimat Trump și consilierii săi reacția Iranului la război . Ce se întâmplă cu prețul petrolului",
      "country": "Iran",
      "url": "https://adevarul.ro/stiri-externe/sua/cum-au-subestimat-trump-si-consilierii-sai-reactia-2514542.html",
      "source_name": "adevarul.ro",
      "timestamp": "20260312T080000Z",
      "language": "Romanian",
      "image": "https://cdn.adh.reperio.news/image-e/eedf0894-1f24-482c-ad11-5b25ae659ec8/index.jpeg?p=f%3Djpeg%26w%3D1200%26h%3D630%26r%3Dcover",
      "lat": 32.43,
      "lng": 53.69
    },
    {
      "id": "gdelt-3908152829",
      "source": "gdelt",
      "category": "protest",
      "title": "泰國散裝貨輪荷莫茲海峽遇襲 船東 ： 3名船員受困 | 國際",
      "country": "",
      "url": "https://www.cna.com.tw:443/news/aopl/202603120183.aspx",
      "source_name": "cna.com.tw",
      "timestamp": "20260312T080000Z",
      "language": "Chinese",
      "image": "",
      "lat": null,
      "lng": null
    },
    {
      "id": "gdelt-1640911541",
      "source": "gdelt",
      "category": "protest",
      "title": "Τραμπ : « Εστιάζουμε με σθένος στα Στενά » - Δηλώσεις για τον πόλεμο με το Ιράν",
      "country": "",
      "url": "https://www.tribune.gr/world/news/article/941419/tramp-estiazoyme-me-sthenos-sta-stena-diloseis-gia-ton-polemo-me-to-iran.html",
      "source_name": "tribune.gr",
      "timestamp": "20260312T080000Z",
      "language": "Greek",
      "image": "https://www.tribune.gr/wp-content/uploads/2026/02/1501713-trump-930-8.jpg",
      "lat": null,
      "lng": null
    },
    {
      "id": "gdelt-2908088900",
      "source": "gdelt",
      "category": "protest",
      "title": "După aproape două săptămâni sub bombe , regimul iranian nu este , deocamdată , în pericol de prăbușire , susțin serviciile secrete americane",
      "country": "Iran",
      "url": "https://adevarul.ro/stiri-externe/in-lume/dupa-aproape-doua-saptamani-sub-bombe-regimul-2514548.html",
      "source_name": "adevarul.ro",
      "timestamp": "20260312T080000Z",
      "language": "Romanian",
      "image": "https://cdn.adh.reperio.news/image-5/50eb888c-7ae8-4f8e-bc1c-b5d6d897431b/index.jpeg?p=f%3Djpeg%26w%3D1200%26h%3D630%26r%3Dcover",
      "lat": 32.43,
      "lng": 53.69
    },
    {
      "id": "gdelt-3836986871",
      "source": "gdelt",
      "category": "protest",
      "title": "Israel coloca dúvidas sobre a sua capacidade de acabar com a teocracia no Irão",
      "country": "Israel",
      "url": "https://jornaleconomico.sapo.pt/noticias/israel-coloca-duvidas-sobre-a-sua-capacidade-de-acabar-com-a-teocracia-no-irao/",
      "source_name": "jornaleconomico.sapo.pt",
      "timestamp": "20260312T080000Z",
      "language": "Portuguese",
      "image": "https://jornaleconomico.sapo.pt/wp-content/uploads/2026/03/DOC.20260303.46679015.12792094-scaled-e1772569286119.jpg",
      "lat": 31.05,
      "lng": 34.85
    },
    {
      "id": "gdelt-2746495624",
      "source": "gdelt",
      "category": "protest",
      "title": "The Latest : Key oil price spikes over $100 as Iranian attacks hit shipping",
      "country": "Iran",
      "url": "https://santamariatimes.com/news/national/the-latest-key-oil-price-spikes-over-100-as-iranian-attacks-hit-shipping/article_94280a49-01ff-5c77-a5a1-d919981a43dc.html",
      "source_name": "santamariatimes.com",
      "timestamp": "20260312T080000Z",
      "language": "English",
      "image": "https://bloximages.chicago2.vip.townnews.com/santamariatimes.com/content/tncms/assets/v3/editorial/9/42/94280a49-01ff-5c77-a5a1-d919981a43dc/69b23f6da93bb.preview.jpg?crop=1464%2C769%2C0%2C103",
      "lat": 32.43,
      "lng": 53.69
    },
    {
      "id": "gdelt-1887726547",
      "source": "gdelt",
      "category": "protest",
      "title": "Rat na Bliskom istoku : Napadi širom Persijskog zaliva , Iran čilja naftna postrojenja",
      "country": "Iran",
      "url": "https://www.nin.rs/svet/vesti/106815/rat-na-bliskom-istoku-napadi-sirom-persijskog-zaliva-iran-cilja-naftna-postrojenja",
      "source_name": "nin.rs",
      "timestamp": "20260312T080000Z",
      "language": "Serbian",
      "image": "https://www.nin.rs/data/images/2026-03-12/104967_tan2026-03-1120521734-0_og.jpg",
      "lat": 32.43,
      "lng": 53.69
    },
    {
      "id": "firms-VIIRS_SNPP_NRT-36.7318-36.21415-2026-03-12-37",
      "source": "firms",
      "category": "thermal_anomaly",
      "title": "Thermal hotspot (low intensity)",
      "lat": 36.7318,
      "lng": 36.21415,
      "brightness": 299.45,
      "frp": 1.05,
      "confidence": "n",
      "intensity": "low",
      "satellite": "VIIRS_SNPP_NRT",
      "timestamp": "2026-03-12T00:37:00Z",
      "daynight": "N"
    },
    {
      "id": "firms-VIIRS_SNPP_NRT-36.87002-34.7638-2026-03-12-37",
      "source": "firms",
      "category": "thermal_anomaly",
      "title": "Thermal hotspot (low intensity)",
      "lat": 36.87002,
      "lng": 34.7638,
      "brightness": 297.36,
      "frp": 1.14,
      "confidence": "n",
      "intensity": "low",
      "satellite": "VIIRS_SNPP_NRT",
      "timestamp": "2026-03-12T00:37:00Z",
      "daynight": "N"
    },
    {
      "id": "firms-VIIRS_SNPP_NRT-36.87234-34.76493-2026-03-12-37",
      "source": "firms",
      "category": "thermal_anomaly",
      "title": "Thermal hotspot (low intensity)",
      "lat": 36.87234,
      "lng": 34.76493,
      "brightness": 295.23,
      "frp": 1.17,
      "confidence": "n",
      "intensity": "low",
      "satellite": "VIIRS_SNPP_NRT",
      "timestamp": "2026-03-12T00:37:00Z",
      "daynight": "N"
    },
    {
      "id": "usgs-us7000s3ku",
      "source": "usgs",
      "category": "earthquake",
      "title": "M 5.1 - 65 km N of Balkanabat, Turkmenistan",
      "place": "65 km N of Balkanabat, Turkmenistan",
      "magnitude": 5.1,
      "depth_km": 10,
      "severity": "major",
      "lat": 40.0936,
      "lng": 54.2446,
      "timestamp": "2026-03-11T07:55:18.615000Z",
      "url": "https://earthquake.usgs.gov/earthquakes/eventpage/us7000s3ku",
      "felt": null,
      "tsunami": 0,
      "alert": null
    },
    {
      "id": "usgs-us7000s2q0",
      "source": "usgs",
      "category": "earthquake",
      "title": "M 4.1 - 74 km W of Bandar Abbas, Iran",
      "place": "74 km W of Bandar Abbas, Iran",
      "magnitude": 4.1,
      "depth_km": 10,
      "severity": "moderate",
      "lat": 27.1417,
      "lng": 55.5298,
      "timestamp": "2026-03-07T03:18:12.799000Z",
      "url": "https://earthquake.usgs.gov/earthquakes/eventpage/us7000s2q0",
      "felt": null,
      "tsunami": 0,
      "alert": null
    },
    {
      "id": "usgs-us7000s2ma",
      "source": "usgs",
      "category": "earthquake",
      "title": "M 4.0 - 12 km S of Yasuj, Iran",
      "place": "12 km S of Yasuj, Iran",
      "magnitude": 4,
      "depth_km": 10,
      "severity": "moderate",
      "lat": 30.56,
      "lng": 51.5632,
      "timestamp": "2026-03-06T17:53:05.714000Z",
      "url": "https://earthquake.usgs.gov/earthquakes/eventpage/us7000s2ma",
      "felt": null,
      "tsunami": 0,
      "alert": null
    }
  ]
}