{
  "source": "gdelt",
  "fetched_at": "2026-03-16T10:55:49.594692Z",
  "region": "west_asia",
  "count": 96,
  "events": [
    {
      "id": "gdelt-2227448677",
      "source": "gdelt",
      "category": "military",
      "title": "Iran War Day 17 : Iran hits Gulf neighbors",
      "country": "Iran",
      "url": "https://www.kmbc.com/article/israel-strikes-beirut-iran-gulf-attacks/70753729",
      "source_name": "kmbc.com",
      "timestamp": "20260316T100000Z",
      "language": "English",
      "image": "https://kubrick.htvapps.com/htv-prod-media.s3.amazonaws.com/images/ap269b7ca5c4498a.jpg?crop=1.00xw:0.846xh;0,0",
      "lat": 32.43,
      "lng": 53.69
    },
    {
      "id": "gdelt-280953740",
      "source": "gdelt",
      "category": "military",
      "title": "  For the victims of Epstein Island : Iran propaganda machine in overdrive",
      "country": "Iran",
      "url": "https://www.yahoo.com/news/articles/victims-epstein-island-iran-propaganda-080000481.html",
      "source_name": "yahoo.com",
      "timestamp": "20260316T100000Z",
      "language": "English",
      "image": "https://s.yimg.com/ny/api/res/1.2/dm.UF4nyVHDFuPlGbQo5rg--/YXBwaWQ9aGlnaGxhbmRlcjt3PTEyMDA7aD03NTA7Y2Y9d2VicA--/https://media.zenfs.com/en/the_telegraph_258/de0ebd62135d8c66bcdb391f71a861b6",
      "lat": 32.43,
      "lng": 53.69
    },
    {
      "id": "gdelt-2159760882",
      "source": "gdelt",
      "category": "military",
      "title": "Georgia Civic & Social Justice Orgs Condemn Illegal War On Iran , U . S . Indiscriminate Killing Of Iranian Citizens",
      "country": "Iran",
      "url": "https://www.scoop.co.nz/stories/WO2603/S00137/georgia-civic-social-justice-orgs-condemn-illegal-war-on-iran-us-indiscriminate-killing-of-iranian-citizens.htm",
      "source_name": "scoop.co.nz",
      "timestamp": "20260316T100000Z",
      "language": "English",
      "image": "http://img.scoop.co.nz/stories/images/1908/scoop_image.jpg",
      "lat": 32.43,
      "lng": 53.69
    },
    {
      "id": "gdelt-1486071832",
      "source": "gdelt",
      "category": "military",
      "title": "Trump zagrozil Natu in evropskim državam : Pomagajte nam pri vojni v Iranu ali pa vas čaka slaba prihodnost",
      "country": "Iran",
      "url": "https://siol.net/novice/svet/trump-zagrozil-natu-in-evropskim-drzavam-pomagajte-nam-pri-vojni-v-iranu-ali-pa-vas-caka-slaba-prihodnost-686946",
      "source_name": "siol.net",
      "timestamp": "20260316T100000Z",
      "language": "Slovenian",
      "image": "https://siol.net/media/img/1d/e1/8990bf7032e3eced689e-donald-trump.jpeg",
      "lat": 32.43,
      "lng": 53.69
    },
    {
      "id": "gdelt-243794254",
      "source": "gdelt",
      "category": "military",
      "title": "Ανάλυση – Πόλεμος στο Ιράν : Το γεωπολιτικό ρήγμα που αλλάζει τη Μέση Ανατολή – Τα πέντε πιθανά σενάρια της επόμενης ημέρας",
      "country": "",
      "url": "https://newpost.gr/eidiseis/analysi-polemos-sto-iran-to-geopolitiko-rigma-poy-allazei-ti-mesi-anatoli-ta-pente-pithana-senaria-tis-epomenis-imeras/",
      "source_name": "newpost.gr",
      "timestamp": "20260316T100000Z",
      "language": "Greek",
      "image": "https://newpost.gr/wp-content/uploads/2024/09/F3RTC3RZ2RMT7GL334I4FOWOGY.jpg",
      "lat": null,
      "lng": null
    },
    {
      "id": "gdelt-1358717779",
      "source": "gdelt",
      "category": "military",
      "title": "  Donald Trump blundered into Iran war - now he wants our kids to pay for his stupidity  ",
      "country": "Iran",
      "url": "https://www.mirror.co.uk/news/us-news/donald-trump-blundered-iran-war-36873121",
      "source_name": "mirror.co.uk",
      "timestamp": "20260316T100000Z",
      "language": "English",
      "image": "https://i2-prod.mirror.co.uk/article36855181.ece/ALTERNATES/s1200d/1_President-Trump-Spends-Weekend-At-Mar-a-Lago-Resort-In-Florida.jpg",
      "lat": 32.43,
      "lng": 53.69
    },
    {
      "id": "gdelt-942334885",
      "source": "gdelt",
      "category": "military",
      "title": "Guerre en Iran : le raid le plus meurtrier de loffensive américano - israélienne détruit une cible non militaire",
      "country": "Iran",
      "url": "https://senego.com/guerre-en-iran-le-raid-le-plus-meurtrier-de-loffensive-americano-israelienne-detruit-une-cible-non-militaire_1937851.html",
      "source_name": "senego.com",
      "timestamp": "20260316T094500Z",
      "language": "French",
      "image": "https://senego.com/wp-content/uploads/2026/03/1773652323_interactive-iran-war-day-16-animated-map-attacks-1773637730-1024x683.webp",
      "lat": 32.43,
      "lng": 53.69
    },
    {
      "id": "gdelt-4003633620",
      "source": "gdelt",
      "category": "military",
      "title": "Trump Has  Won Iran War , Then Why Does He Need Foreign Ships To End It ? 3 Reasons Explained | Explainers News",
      "country": "Iran",
      "url": "https://www.news18.com/explainers/trump-claimed-us-has-won-iran-war-then-why-does-he-need-foreign-ships-to-end-it-3-reasons-explained-ws-kl-9962930.html",
      "source_name": "news18.com",
      "timestamp": "20260316T094500Z",
      "language": "English",
      "image": "https://images.news18.com/ibnlive/uploads/2026/02/trump-2026-02-2ed70224da512233a88008a100f624bb-1200x675.jpg",
      "lat": 32.43,
      "lng": 53.69
    },
    {
      "id": "gdelt-1693261830",
      "source": "gdelt",
      "category": "military",
      "title": "КОЛУМНА I Дали живееме во ера на постојани економски кризи ? ",
      "country": "",
      "url": "https://time.mk/c/ac580d3184/kolumna-i-dali-ziveeme-vo-era-na-postojani-ekonomski-krizi.html",
      "source_name": "time.mk",
      "timestamp": "20260316T094500Z",
      "language": "Macedonian",
      "image": "http://pari.com.mk/wp-content/uploads/2026/03/Pari_Kolumna_Georgieva-Svrtinov_Ekonomski-krizi_2.jpg",
      "lat": null,
      "lng": null
    },
    {
      "id": "gdelt-3775031632",
      "source": "gdelt",
      "category": "military",
      "title": "허프포스트코리아",
      "country": "",
      "url": "https://www.huffingtonpost.kr:443/article/250318",
      "source_name": "huffingtonpost.kr",
      "timestamp": "20260316T094500Z",
      "language": "Korean",
      "image": "https://cdn.huffingtonpost.kr/news/photo/202603/202603161623.jpg?v=250318",
      "lat": null,
      "lng": null
    },
    {
      "id": "gdelt-1008908800",
      "source": "gdelt",
      "category": "military",
      "title": "Donald Trump droht Nato und fordert Hilfe in Straße von Hormus",
      "country": "",
      "url": "https://www.onvista.de/news/2026/03-16-roundup-trump-droht-nato-und-fordert-hilfe-in-strasse-von-hormus-0-10-26490059",
      "source_name": "onvista.de",
      "timestamp": "20260316T094500Z",
      "language": "German",
      "image": "https://images.onvista.com/onvista-media/image/upload/c_fill,h_630,w_1200/v1/article/tfslmhortaz7v95ltkej",
      "lat": null,
      "lng": null
    },
    {
      "id": "gdelt-45903188",
      "source": "gdelt",
      "category": "military",
      "title": "اسرائیلی فوج نے لبنان میں حزب اللہ کے خلاف زمینی کارروائی کا آغاز کردیا - World",
      "country": "",
      "url": "https://www.aaj.tv/news/30501798/",
      "source_name": "aaj.tv",
      "timestamp": "20260316T094500Z",
      "language": "Urdu",
      "image": "",
      "lat": null,
      "lng": null
    },
    {
      "id": "gdelt-2918518350",
      "source": "gdelt",
      "category": "military",
      "title": "德黑蘭天降有毒黑雨 ： 美伊衝突連轟基礎設施 ， 水與石油淪為軍事籌碼 - TNL The News Lens 關鍵評論網",
      "country": "",
      "url": "https://www.thenewslens.com/article/265465",
      "source_name": "thenewslens.com",
      "timestamp": "20260316T094500Z",
      "language": "Chinese",
      "image": "https://bucket-image.inkmaginecms.com/version/social/9dde7c0f-a597-445c-80dd-9a93db8a4006/image/2026/03/270473d3-fa11-486d-905e-1456eaf09802.jpg",
      "lat": null,
      "lng": null
    },
    {
      "id": "gdelt-4155175127",
      "source": "gdelt",
      "category": "military",
      "title": "USS Abraham Lincoln moves farther from Iran after reported drone threats",
      "country": "Iran",
      "url": "https://tribune.com.pk/story/2597900/uss-abraham-lincoln-moves-farther-from-iran-after-reported-drone-threats",
      "source_name": "tribune.com.pk",
      "timestamp": "20260316T094500Z",
      "language": "English",
      "image": "https://i.tribune.com.pk/media/images/iran1771552108-0/iran1771552108-0-640x480.webp",
      "lat": 32.43,
      "lng": 53.69
    },
    {
      "id": "gdelt-1517466964",
      "source": "gdelt",
      "category": "military",
      "title": "MFA updates number of Armenians stranded in Asia",
      "country": "",
      "url": "https://panarmenian.net/eng/news/331594/",
      "source_name": "panarmenian.net",
      "timestamp": "20260316T094500Z",
      "language": "English",
      "image": "",
      "lat": null,
      "lng": null
    },
    {
      "id": "gdelt-4212118926",
      "source": "gdelt",
      "category": "military",
      "title": "Iran does not fight to win , but to endure",
      "country": "Iran",
      "url": "https://www.dailysabah.com/opinion/op-ed/iran-does-not-fight-to-win-but-to-endure",
      "source_name": "dailysabah.com",
      "timestamp": "20260316T094500Z",
      "language": "English",
      "image": "https://idsb.tmgrup.com.tr/ly/uploads/images/2026/03/16/thumbs/1200x675/431764.jpg",
      "lat": 32.43,
      "lng": 53.69
    },
    {
      "id": "gdelt-1641337809",
      "source": "gdelt",
      "category": "military",
      "title": "Israel diz ter destruído avião do anterior líder supremo do Irão . Um morto em Abu Dhabi após queda de míssil",
      "country": "Israel",
      "url": "https://sapo.pt/artigo/israel-diz-ter-destruido-aviao-do-anterior-lider-supremo-do-irao-um-morto-em-abu-dhabi-apos-queda-de-missil-69b7caf09009c4d56112bb53",
      "source_name": "sapo.pt",
      "timestamp": "20260316T094500Z",
      "language": "Portuguese",
      "image": "https://media.assettype.com/dn/2026-03-16/p7zgi836/DOC.20260315.46756421.12821312.jpg",
      "lat": 31.05,
      "lng": 34.85
    },
    {
      "id": "gdelt-1104609932",
      "source": "gdelt",
      "category": "military",
      "title": "Between Iran and a Hard Place : Wall Street Weighs War and Stagflation Risks",
      "country": "Iran",
      "url": "https://www.investing.com/analysis/between-iran-and-a-hard-place-wall-street-weighs-war-and-stagflation-risks-200676670",
      "source_name": "investing.com",
      "timestamp": "20260316T094500Z",
      "language": "English",
      "image": "https://i-invdn-com.investing.com/redesign/images/seo/investingcom_analysis_og.jpg",
      "lat": 32.43,
      "lng": 53.69
    },
    {
      "id": "gdelt-298253378",
      "source": "gdelt",
      "category": "military",
      "title": "تمارا حداد : إسرائيل حققت 70 % من أهدافها العسكرية للحرب على إيران",
      "country": "",
      "url": "https://www.dostor.org/5460427",
      "source_name": "dostor.org",
      "timestamp": "20260316T094500Z",
      "language": "Arabic",
      "image": "",
      "lat": null,
      "lng": null
    },
    {
      "id": "gdelt-800972198",
      "source": "gdelt",
      "category": "military",
      "title": "  미 · 이란 전쟁 여파 … 유가 10 % 상승 시 제조업 생산비 0 . 71 % 증가  ",
      "country": "",
      "url": "http://www.metroseoul.co.kr/article/20260316500548",
      "source_name": "metroseoul.co.kr",
      "timestamp": "20260316T094500Z",
      "language": "Korean",
      "image": "http://cdn.emetro.co.kr/data2/content/image/2026/03/16/.cache/512/20260316500549.jpg",
      "lat": null,
      "lng": null
    },
    {
      "id": "gdelt-2365851076",
      "source": "gdelt",
      "category": "military",
      "title": "Hungarian Troops and Diplomats Withdrawn from Erbil Base in Iraq",
      "country": "Iraq",
      "url": "https://hungarytoday.hu/hungarian-troops-and-diplomats-withdrawn-from-erbil-base-in-iraq/",
      "source_name": "hungarytoday.hu",
      "timestamp": "20260316T094500Z",
      "language": "English",
      "image": "https://hungarytoday.hu/wp-content/uploads/2026/03/69b5c2aa86171424823048.jpg",
      "lat": 33.22,
      "lng": 43.68
    },
    {
      "id": "gdelt-1050799421",
      "source": "gdelt",
      "category": "military",
      "title": "Iran war : Israel says it has enough interceptors but for how long ? ",
      "country": "Israel",
      "url": "https://www.firstpost.com/world/iran-war-israel-interceptors-air-defence-iran-attacks-west-asia-conflict-gulf-strikes-13990022.html",
      "source_name": "firstpost.com",
      "timestamp": "20260316T094500Z",
      "language": "English",
      "image": "https://images.firstpost.com/uploads/2026/03/tehran-2026-03-1c6eabb58e4133c8455741b3766cca47.jpg?im=FitAndFill=(1200,675)",
      "lat": 31.05,
      "lng": 34.85
    },
    {
      "id": "gdelt-3658057200",
      "source": "gdelt",
      "category": "military",
      "title": "Iran live updates : Dubai airport resumes some flights after drone impact sparks fuel tank fire",
      "country": "Iran",
      "url": "https://abcnews.com/International/live-updates/iran-live-updates/?id=131108492",
      "source_name": "abcnews.com",
      "timestamp": "20260316T094500Z",
      "language": "English",
      "image": "https://i.abcnewsfe.com/a/46d5bc16-6f3b-42a7-a05a-cf7abffd5514/dubai-airport-main_1773646515530_hpMain_16x9.jpg",
      "lat": 32.43,
      "lng": 53.69
    },
    {
      "id": "gdelt-4035785708",
      "source": "gdelt",
      "category": "military",
      "title": "Το Στενό του Ορμούζ στο χείλος της στρατηγικής κρίσης και το « στοίχημα » της ναυτικής αποτροπής",
      "country": "",
      "url": "https://athina984.gr/2026/03/16/to-steno-toy-ormoyz-sto-cheilos-tis-stratigikis-krisis-kai-to-stoichima-tis-naytikis-apotropis/",
      "source_name": "athina984.gr",
      "timestamp": "20260316T094500Z",
      "language": "Greek",
      "image": "https://athina984.gr/wp-content/uploads/2026/03/%CE%91%CE%A3%CE%A0%CE%99%CE%94%CE%95%CE%A3.webp",
      "lat": null,
      "lng": null
    },
    {
      "id": "gdelt-1749678882",
      "source": "gdelt",
      "category": "military",
      "title": "WHO releases $2mn in emergency funds for Middle East health",
      "country": "",
      "url": "https://www.muscatdaily.com/2026/03/16/who-releases-2mn-in-emergency-funds-for-middle-east-health/",
      "source_name": "muscatdaily.com",
      "timestamp": "20260316T094500Z",
      "language": "English",
      "image": "https://www.muscatdaily.com/wp-content/uploads/2026/03/WHO-releases-2mn-in-emergency-funds-for-Middle-East-health-crisis.jpg",
      "lat": null,
      "lng": null
    },
    {
      "id": "gdelt-3087122280",
      "source": "gdelt",
      "category": "military",
      "title": "Shtohen tensionet mes Serbisë dhe Kroacisë , Milanoviç - Vuçiç përplasen për raketat kineze dhe akuzat për aleancë ... - Sot News",
      "country": "",
      "url": "https://sot.com.al/rajoni/shtohen-tensionet-mes-serbise-dhe-kroacise-milanovic-vucic-perplasen-per-raketat-kineze-dhe-akuzat-per-aleance/",
      "source_name": "sot.com.al",
      "timestamp": "20260316T093000Z",
      "language": "Albanian",
      "image": "https://sot.com.al/wp-content/uploads/2026/03/rajon-fq-12-vucic-kroacia.jpg",
      "lat": null,
      "lng": null
    },
    {
      "id": "gdelt-1743236072",
      "source": "gdelt",
      "category": "military",
      "title": "Parteien gegen deutsche Beteiligung an US - Militärmission",
      "country": "",
      "url": "https://www.wallstreet-online.de/nachricht/20616944-parteien-deutsche-beteiligung-us-militaermission",
      "source_name": "wallstreet-online.de",
      "timestamp": "20260316T093000Z",
      "language": "German",
      "image": "https://assets.wallstreet-online.de/_media/3129/rohstoffe/size_645/chemiepark-leuna-raffinerie-dpa-jan-woitas.jpg",
      "lat": null,
      "lng": null
    },
    {
      "id": "gdelt-2537875806",
      "source": "gdelt",
      "category": "military",
      "title": "Lübnan , UNIFIL glerine ülkenin güneyinde yapılan saldırıyı kınadı",
      "country": "",
      "url": "https://www.haberler.com/guncel/lubnan-unifil-guclerine-yonelik-saldirilari-kinadi-19662099-haberi/",
      "source_name": "haberler.com",
      "timestamp": "20260316T093000Z",
      "language": "Turkish",
      "image": "",
      "lat": null,
      "lng": null
    },
    {
      "id": "gdelt-3204584905",
      "source": "gdelt",
      "category": "military",
      "title": "Are Iran  Mosaic Defence  and  Fourth Successor  Models Ensuring the Regime Survival ? | Kashmir Life",
      "country": "Iran",
      "url": "https://kashmirlife.net/are-irans-mosaic-defence-and-fourth-successor-models-ensuring-the-regimes-survival-428552/",
      "source_name": "kashmirlife.net",
      "timestamp": "20260316T093000Z",
      "language": "English",
      "image": "https://kashmirlife.net/wp-content/uploads/2026/03/Mojataba-Khamenei-reportedly-Irans-New-Supreme-Leader.webp",
      "lat": 32.43,
      "lng": 53.69
    },
    {
      "id": "gdelt-2371900527",
      "source": "gdelt",
      "category": "military",
      "title": "İsrail ordusu bu gecə Livanda quru əməliyyatlarına başlayıb",
      "country": "",
      "url": "https://anspress.com/israil-ordusu-bu-gece-livanda-quru-emeliyyatlarina-bashlayib",
      "source_name": "anspress.com",
      "timestamp": "20260316T093000Z",
      "language": "Azerbaijani",
      "image": "https://anspress.com/uploads/images/2026/03/image_750x_69b7b529e8a7f.jpg",
      "lat": null,
      "lng": null
    },
    {
      "id": "gdelt-2361346522",
      "source": "gdelt",
      "category": "military",
      "title": "  PM Modi undermining BRICS presidency to please Trump : Jairam Ramesh questions  silence  on US actions",
      "country": "",
      "url": "http://www.calcuttanews.net/news/278924865/pm-modi-undermining-brics-presidency-to-please-trump-jairam-ramesh-questions-ilence-on-us-actions",
      "source_name": "calcuttanews.net",
      "timestamp": "20260316T093000Z",
      "language": "English",
      "image": "https://image.chitra.live/api/v1/wps/99b38d6/2ac9138b-2db5-4bc6-a295-e2ae95a9c227/0/ANI-20260316052119-600x315.jpg",
      "lat": null,
      "lng": null
    },
    {
      "id": "gdelt-1479703167",
      "source": "gdelt",
      "category": "military",
      "title": "Ýran Füzesi Ýsrailin Merkezine Ýsabet Etti",
      "country": "",
      "url": "https://www.memurlar.net/haber/1162187/iran-fuzesi-israil-in-merkezine-isabet-etti.html",
      "source_name": "memurlar.net",
      "timestamp": "20260316T093000Z",
      "language": "Turkish",
      "image": "https://www.memurlar.net/common/news/images/1162187/headline.jpg",
      "lat": null,
      "lng": null
    },
    {
      "id": "gdelt-11676824",
      "source": "gdelt",
      "category": "military",
      "title": "Lebanese influencer Natalie Kamal El - Din fighting for life after Israel attack that killed her husband , daughter",
      "country": "Israel",
      "url": "https://www.hindustantimes.com/trending/lebanese-influencer-natalie-kamal-el-din-fighting-for-life-after-israel-attack-that-killed-her-husband-daughter-101773650414522.html",
      "source_name": "hindustantimes.com",
      "timestamp": "20260316T093000Z",
      "language": "English",
      "image": "https://www.hindustantimes.com/ht-img/img/2026/03/16/550x309/nataliekamaledine_1773651007545_1773651007693.jpg",
      "lat": 31.05,
      "lng": 34.85
    },
    {
      "id": "gdelt-2046859741",
      "source": "gdelt",
      "category": "military",
      "title": "باحثة : مبادرة فرنسية بالتوازي مع التطورات العسكرية في لبنان و  بري  يعترض",
      "country": "",
      "url": "https://www.dostor.org/5460413",
      "source_name": "dostor.org",
      "timestamp": "20260316T093000Z",
      "language": "Arabic",
      "image": "",
      "lat": null,
      "lng": null
    },
    {
      "id": "gdelt-3346012926",
      "source": "gdelt",
      "category": "military",
      "title": "Ветеран заявил , что Украина проиграла  битву за мнения  ",
      "country": "",
      "url": "https://society.comments.ua/news/warrussia/my-uzhe-proigrali-etu-bitvu-v-vsu-zabili-trevogu-iz-za-krayne-sereznoy-problemy-800772.html",
      "source_name": "society.comments.ua",
      "timestamp": "20260316T093000Z",
      "language": "Russian",
      "image": "https://comments.ua/img/facebooks_img/YOJse6IclmvtZ_s5UP4DASBV4aa4cbIY.jpg",
      "lat": null,
      "lng": null
    },
    {
      "id": "gdelt-3082857059",
      "source": "gdelt",
      "category": "military",
      "title": "PNG must not follow Australia into war",
      "country": "",
      "url": "https://www.thenational.com.pg/png-must-not-follow-australia-into-war/",
      "source_name": "thenational.com.pg",
      "timestamp": "20260316T093000Z",
      "language": "English",
      "image": "",
      "lat": null,
      "lng": null
    },
    {
      "id": "gdelt-1672013401",
      "source": "gdelt",
      "category": "military",
      "title": "İran füzesi İsrailin merkezine isabet etti",
      "country": "Iran",
      "url": "https://www.trthaber.com/haber/dunya/iran-fuzesi-israilin-merkezine-isabet-etti-937950.html",
      "source_name": "trthaber.com",
      "timestamp": "20260316T093000Z",
      "language": "Turkish",
      "image": "https://trthaberstatic.cdn.wp.trt.com.tr/resimler/2444000/tel-aviv-ap-2444721.jpg",
      "lat": 32.43,
      "lng": 53.69
    },
    {
      "id": "gdelt-280442691",
      "source": "gdelt",
      "category": "military",
      "title": "Τραμπ : Aπαιτεί από συμμάχους - Κίνα να αναπτύξουν πολεμικά πλοία στο Ορμούζ",
      "country": "",
      "url": "https://www.skai.gr/news/world/tramp-apaitei-apo-symmaxous-kina-na-anaptyksoun-polemika-ploia-sto-ormouz",
      "source_name": "skai.gr",
      "timestamp": "20260316T093000Z",
      "language": "Greek",
      "image": "https://cdn.skai.gr/sites/default/files/styles/article_16_9/public/2026-03/ap26075041437017-trump.jpg?itok=F9E0kyJI",
      "lat": null,
      "lng": null
    },
    {
      "id": "gdelt-1646858487",
      "source": "gdelt",
      "category": "military",
      "title": "Iran - Führer Modschtaba Chamenei in Moskau ? Bericht über Not - OP in Putins Palast",
      "country": "Iran",
      "url": "https://www.merkur.de/politik/iran-fuehrer-chamenei-in-moskau-bericht-ueber-not-op-in-putins-palast-zr-94219667.html",
      "source_name": "merkur.de",
      "timestamp": "20260316T093000Z",
      "language": "German",
      "image": "",
      "lat": 32.43,
      "lng": 53.69
    },
    {
      "id": "gdelt-692463205",
      "source": "gdelt",
      "category": "military",
      "title": "পারমাণবিক অস্ত্রে ঝুঁকতে পারে ইসরাইল",
      "country": "",
      "url": "https://www.jugantor.com/international/1078368",
      "source_name": "jugantor.com",
      "timestamp": "20260316T093000Z",
      "language": "Bengali",
      "image": "https://cdn.jugantor.com/assets/news_photos/2026/03/16/social-thumbnail/22-69b7c65be8a94.jpg",
      "lat": null,
      "lng": null
    },
    {
      "id": "gdelt-3920491313",
      "source": "gdelt",
      "category": "military",
      "title": "Το Ισραήλ ξεκινά χερσαίες επιθέσεις κατά του Λιβάνου - Ξεπερνούν τους 3 . 000 οι νεκροί στο Ιράν - The Press Project",
      "country": "",
      "url": "https://thepressproject.gr/to-israil-xekina-chersaies-epitheseis-kata-tou-livanou-xepernoun-tous-3-000-oi-nekroi-sto-iran/",
      "source_name": "thepressproject.gr",
      "timestamp": "20260316T093000Z",
      "language": "Greek",
      "image": "https://thepressproject.gr/app/uploads/2026/03/thumbs-b-c-83704a2f918d33b3d8e531cb3a117298.jpg",
      "lat": null,
      "lng": null
    },
    {
      "id": "gdelt-2517122426",
      "source": "gdelt",
      "category": "military",
      "title": "川普促護航荷姆茲海峽 警告歐 . 中恐面臨不利 | 國際",
      "country": "",
      "url": "https://news.ustv.com.tw/newsdetail/20260316A049",
      "source_name": "news.ustv.com.tw",
      "timestamp": "20260316T093000Z",
      "language": "Chinese",
      "image": "https://cdn.ustv.com.tw/new_newsimg/20260316/A049/20260316A049_154603.jpg",
      "lat": null,
      "lng": null
    },
    {
      "id": "gdelt-314004865",
      "source": "gdelt",
      "category": "military",
      "title": "Yön uutiskooste | Trump : Iran ei ole valmis sopimukseen , s lämpenee loppuviikosta , ennakkosuosikit jyräsivät Oscar - gaalassa",
      "country": "Iran",
      "url": "https://www.ita-savo.fi/uutissuomalainen/9301098",
      "source_name": "ita-savo.fi",
      "timestamp": "20260316T093000Z",
      "language": "Finnish",
      "image": "https://i.media.fi/incoming/kl08or/11346041.jpg/alternates/OG_IMAGE_ITA_SAVO/11346041.jpg",
      "lat": 32.43,
      "lng": 53.69
    },
    {
      "id": "gdelt-2706425465",
      "source": "gdelt",
      "category": "military",
      "title": "Трамп пошел на жесткий шаг : обратился к нескольким странам и серьезно предупредил НАТО",
      "country": "",
      "url": "https://www.9tv.co.il/item/210812",
      "source_name": "9tv.co.il",
      "timestamp": "20260316T093000Z",
      "language": "Russian",
      "image": "https://www.9tv.co.il/download/pictures/img_id_49047.JPG",
      "lat": null,
      "lng": null
    },
    {
      "id": "gdelt-386751344",
      "source": "gdelt",
      "category": "military",
      "title": "Trump yönetimi , İrana saldırıların maliyetini açıkladı",
      "country": "",
      "url": "https://www.trthaber.com/haber/dunya/trump-yonetimi-irana-saldirilarin-maliyetini-acikladi-937944.html",
      "source_name": "trthaber.com",
      "timestamp": "20260316T093000Z",
      "language": "Turkish",
      "image": "https://trthaberstatic.cdn.wp.trt.com.tr/resimler/2440000/trump-iran-2440352.jpg",
      "lat": null,
      "lng": null
    },
    {
      "id": "gdelt-443295121",
      "source": "gdelt",
      "category": "military",
      "title": "Iran War : NLC Makes 5 Demands From FG Over Rising Price Of Petrol",
      "country": "Iran",
      "url": "https://www.naijanews.com/2026/03/16/nlc-5-demands-fg-price-petrol/",
      "source_name": "naijanews.com",
      "timestamp": "20260316T093000Z",
      "language": "English",
      "image": "https://www.naijanews.com/wp-content/uploads/2023/12/Joe-Ajaero-1-1000x600.jpg.webp",
      "lat": 32.43,
      "lng": 53.69
    },
    {
      "id": "gdelt-2718787445",
      "source": "gdelt",
      "category": "military",
      "title": "Ливан - Израиль начал вторжение в страну",
      "country": "",
      "url": "https://www.unian.net/world/izrail-nachal-vtorzhenie-v-livan-13316496.html",
      "source_name": "unian.net",
      "timestamp": "20260316T093000Z",
      "language": "Russian",
      "image": "https://images.unian.net/photos/2026_03/thumb_files/620_324_1773650755-1332.jpg?1",
      "lat": null,
      "lng": null
    },
    {
      "id": "gdelt-840877481",
      "source": "gdelt",
      "category": "military",
      "title": "アングル ： 中東緊迫で市場は2022年の教訓参照 ロシアのウクライナ侵攻時の動き再検証",
      "country": "",
      "url": "https://jp.reuters.com/opinion/EO465USSX5JA7IS2ONUJ3UUOL4-2026-03-16/",
      "source_name": "jp.reuters.com",
      "timestamp": "20260316T093000Z",
      "language": "Japanese",
      "image": "https://www.reuters.com/resizer/v2/HTF6WGP3MRLB5FQTSLZSDIATIA.jpg?auth=046676528ee91e0006eeb27f87722de09217c891169252fd50ed72af50c56642&quality=80&smart=true",
      "lat": null,
      "lng": null
    },
    {
      "id": "gdelt-3798535126",
      "source": "gdelt",
      "category": "military",
      "title": "Oil rises further above $100 , stocks mixed as Iran war rages",
      "country": "Iran",
      "url": "https://www.bransontrilakesnews.com/news/national/article_191fe53b-1a08-5201-a132-072609a32f58.html",
      "source_name": "bransontrilakesnews.com",
      "timestamp": "20260316T093000Z",
      "language": "English",
      "image": "https://bloximages.chicago2.vip.townnews.com/bransontrilakesnews.com/content/tncms/assets/v3/editorial/1/2a/12a1d99d-1ee5-5694-bd49-b75372142b49/69b7840c4a643.image.jpg?crop=341%2C341%2C85%2C0",
      "lat": 32.43,
      "lng": 53.69
    },
    {
      "id": "gdelt-3647714004",
      "source": "gdelt",
      "category": "military",
      "title": "ইসরাইল প্রধানমন্ত্রী মোদির সফরের দুদিন পর ইরানে হামলার অনুমোদন দিয়েছে , দূত বলেছেন",
      "country": "",
      "url": "https://banglanews24.today/2026/03/16/%E0%A6%87%E0%A6%B8%E0%A6%B0%E0%A6%BE%E0%A6%87%E0%A6%B2-%E0%A6%AA%E0%A7%8D%E0%A6%B0%E0%A6%A7%E0%A6%BE%E0%A6%A8%E0%A6%AE%E0%A6%A8%E0%A7%8D%E0%A6%A4%E0%A7%8D%E0%A6%B0%E0%A7%80-%E0%A6%AE%E0%A7%8B%E0%A6%A6/",
      "source_name": "banglanews24.today",
      "timestamp": "20260316T093000Z",
      "language": "Bengali",
      "image": "https://akm-img-a-in.tosshub.com/indiatoday/images/story/202603/prime-minister-narendra-modi-with-his-israeli-counterpart-benjamin-netanyahu-in-jerusalem-during-his-163852172-16x9_0.jpg?VersionId=BcOtKMMMyJ_W0XmL2H2LuwmQVVoU_qXN",
      "lat": null,
      "lng": null
    },
    {
      "id": "gdelt-1665251622",
      "source": "gdelt",
      "category": "humanitarian",
      "title": "Trump warns Nato allies over Iran response as Starmer pledges heating oil help",
      "country": "Iran",
      "url": "https://www.darlingtonandstocktontimes.co.uk/news/national/25938534.trump-warns-nato-allies-iran-response-starmer-pledges-heating-oil-help/",
      "source_name": "darlingtonandstocktontimes.co.uk",
      "timestamp": "20260316T100000Z",
      "language": "English",
      "image": "https://www.darlingtonandstocktontimes.co.uk/resources/images/20661973.jpg?type=og-image",
      "lat": 32.43,
      "lng": 53.69
    },
    {
      "id": "gdelt-2890334006",
      "source": "gdelt",
      "category": "humanitarian",
      "title": "Španjolski glumac nosio natpis na dodjeli Oscara : Evo što znači",
      "country": "",
      "url": "https://www.24sata.hr/show/spanjolski-glumac-nosio-natpis-na-dodjeli-oscara-evo-sto-znaci-1114901",
      "source_name": "24sata.hr",
      "timestamp": "20260316T094500Z",
      "language": "Bosnian",
      "image": "https://img.24sata.hr/PcHemfRbMIim9GaRs4pHSqMsxCs=/1200x630/smart/media/images/2026-11/2026-03-16t044036z-2028993397-hp1em3g0czmgx-rtrmadp-3-awards-oscars-tdgvaa1.jpg",
      "lat": null,
      "lng": null
    },
    {
      "id": "gdelt-1517322930",
      "source": "gdelt",
      "category": "humanitarian",
      "title": "Trump warns Nato allies over Iran response as Starmer pledges heating oil help",
      "country": "Iran",
      "url": "https://www.newsandstar.co.uk/news/national/25938534.trump-warns-nato-allies-iran-response-starmer-pledges-heating-oil-help/",
      "source_name": "newsandstar.co.uk",
      "timestamp": "20260316T094500Z",
      "language": "English",
      "image": "https://www.newsandstar.co.uk/resources/images/20661973.jpg?type=og-image",
      "lat": 32.43,
      "lng": 53.69
    },
    {
      "id": "gdelt-1210299087",
      "source": "gdelt",
      "category": "humanitarian",
      "title": "  원 배틀  오스카 작품상 등 6관왕 … 전쟁 끝내야  목소리도 - 국민일보",
      "country": "",
      "url": "https://www.kmib.co.kr/article/view.asp?arcid=0029535092&code=61181511&sid1=ens",
      "source_name": "kmib.co.kr",
      "timestamp": "20260316T094500Z",
      "language": "Korean",
      "image": "https://image.kmib.co.kr/online_image/2026/0316/2026031615572093843_1773644242_0029535092.jpg",
      "lat": null,
      "lng": null
    },
    {
      "id": "gdelt-1789874356",
      "source": "gdelt",
      "category": "humanitarian",
      "title": "HAOS U DUBAIJU ! Pokrenuta kopnena operacija , Tramp zapretio NATO paktu ! ",
      "country": "",
      "url": "https://www.alo.rs/vesti/svet/16648928/haos-u-dubaiju-preusmereni-svi-letovi-u-toku-presretanje-raketa.html",
      "source_name": "alo.rs",
      "timestamp": "20260316T094500Z",
      "language": "Serbian",
      "image": "https://www.alo.rs/upload/thumb/2026/3/16/7/52/715/2912318/usgs-WOF7xn1antA-unsplash.jpg",
      "lat": null,
      "lng": null
    },
    {
      "id": "gdelt-355074266",
      "source": "gdelt",
      "category": "humanitarian",
      "title": "Trump warns Nato allies over Iran response as Starmer pledges heating oil help",
      "country": "Iran",
      "url": "https://www.chesterstandard.co.uk/news/national/25938534.trump-warns-nato-allies-iran-response-starmer-pledges-heating-oil-help/",
      "source_name": "chesterstandard.co.uk",
      "timestamp": "20260316T093000Z",
      "language": "English",
      "image": "https://www.chesterstandard.co.uk/resources/images/20661973.jpg?type=og-image",
      "lat": 32.43,
      "lng": 53.69
    },
    {
      "id": "gdelt-405837424",
      "source": "gdelt",
      "category": "humanitarian",
      "title": "Trump warns Nato allies over Iran response as Starmer pledges heating oil help",
      "country": "Iran",
      "url": "https://www.halesowennews.co.uk/news/national/25938534.trump-warns-nato-allies-iran-response-starmer-pledges-heating-oil-help/",
      "source_name": "halesowennews.co.uk",
      "timestamp": "20260316T093000Z",
      "language": "English",
      "image": "https://www.halesowennews.co.uk/resources/images/20661973.jpg?type=og-image",
      "lat": 32.43,
      "lng": 53.69
    },
    {
      "id": "gdelt-27169814",
      "source": "gdelt",
      "category": "humanitarian",
      "title": "Trump warns Nato allies over Iran response as Starmer pledges heating oil help",
      "country": "Iran",
      "url": "https://www.countypress.co.uk/news/national/25938534.trump-warns-nato-allies-iran-response-starmer-pledges-heating-oil-help/",
      "source_name": "countypress.co.uk",
      "timestamp": "20260316T093000Z",
      "language": "English",
      "image": "https://www.countypress.co.uk/resources/images/20661973.jpg?type=og-image",
      "lat": 32.43,
      "lng": 53.69
    },
    {
      "id": "gdelt-2009710813",
      "source": "gdelt",
      "category": "humanitarian",
      "title": "SÌ , viaggiare … ma c  È una guerra da evitare – il conflitto in iran sta scombinando i piani di ... ",
      "country": "Iran",
      "url": "https://www.dagospia.com/cronache/si-viaggiare-c-e-guerra-evitare-conflitto-in-iran-sta-scombinando-i-467552",
      "source_name": "dagospia.com",
      "timestamp": "20260316T093000Z",
      "language": "Italian",
      "image": "https://static.dagospia.com/img/patch/03-2026/istanbul-2242881_600_q50.webp",
      "lat": 32.43,
      "lng": 53.69
    },
    {
      "id": "gdelt-3721957618",
      "source": "gdelt",
      "category": "humanitarian",
      "title": "Trump warns Nato allies over Iran response as Starmer pledges heating oil help",
      "country": "Iran",
      "url": "https://www.cravenherald.co.uk/news/national/25938534.trump-warns-nato-allies-iran-response-starmer-pledges-heating-oil-help/",
      "source_name": "cravenherald.co.uk",
      "timestamp": "20260316T093000Z",
      "language": "English",
      "image": "https://www.cravenherald.co.uk/resources/images/20661973.jpg?type=og-image",
      "lat": 32.43,
      "lng": 53.69
    },
    {
      "id": "gdelt-2267896006",
      "source": "gdelt",
      "category": "humanitarian",
      "title": "Última hora de la guerra en Oriente Medio | La UE dice que Ormuz está fuera del ámbito de la OTAN",
      "country": "",
      "url": "https://www.diariosur.es/internacional/oriente-proximo/sigue-directo-ultima-hora-guerra-oriente-medio-20260316165828-dirc.html",
      "source_name": "diariosur.es",
      "timestamp": "20260316T093000Z",
      "language": "Spanish",
      "image": "https://s3.ppllstatics.com/rc/www/multimedia/2026/03/16/iran-directo-lunes-RDnaTfyRKY0fxbdcNbfvCRN-1200x840@RC.JPG",
      "lat": null,
      "lng": null
    },
    {
      "id": "gdelt-4053313971",
      "source": "gdelt",
      "category": "humanitarian",
      "title": "Miliony migrantów ruszą na Europę ? Szefowa KE ostrzega",
      "country": "",
      "url": "https://forsal.pl/swiat/unia-europejska/artykuly/11214766,miliony-migrantow-rusza-na-europe-szefowa-ke-ostrzega.html",
      "source_name": "forsal.pl",
      "timestamp": "20260316T093000Z",
      "language": "Polish",
      "image": "https://ocdn.eu/pulscms-transforms/1/iH6ktkuTURBXy9mMWQ0ZjA5My01ZTZhLTRhODgtYTIwNS1jZGRjZjQ4YTE4ZGUuanBlZ5GTBc0EsM0CdA",
      "lat": null,
      "lng": null
    },
    {
      "id": "gdelt-155939328",
      "source": "gdelt",
      "category": "humanitarian",
      "title": "Trump warns Nato allies over Iran response as Starmer pledges heating oil help",
      "country": "Iran",
      "url": "https://www.burytimes.co.uk/news/national/25938534.trump-warns-nato-allies-iran-response-starmer-pledges-heating-oil-help/",
      "source_name": "burytimes.co.uk",
      "timestamp": "20260316T091500Z",
      "language": "English",
      "image": "https://www.burytimes.co.uk/resources/images/20661973.jpg?type=og-image",
      "lat": 32.43,
      "lng": 53.69
    },
    {
      "id": "gdelt-1232878190",
      "source": "gdelt",
      "category": "humanitarian",
      "title": "Мьянма возобновила работу парламента при жестком контроле военных | MigNews - Новости Израиля и Мира на русском языке",
      "country": "",
      "url": "https://mignews.com/news/politic/myanma-vozobnovila-rabotu-parlamenta-pri-zhestkom-kontrole-voennyh.html",
      "source_name": "mignews.com",
      "timestamp": "20260316T091500Z",
      "language": "Russian",
      "image": "https://mignews.com/media/cache/41/67/41674d2d4f52605fb1b1677e745a6bf0.jpg",
      "lat": null,
      "lng": null
    },
    {
      "id": "gdelt-2098683958",
      "source": "gdelt",
      "category": "humanitarian",
      "title": "Trump warns Nato allies over Iran response as Starmer pledges heating oil help",
      "country": "Iran",
      "url": "https://www.messengernewspapers.co.uk/news/national/25938534.trump-warns-nato-allies-iran-response-starmer-pledges-heating-oil-help/",
      "source_name": "messengernewspapers.co.uk",
      "timestamp": "20260316T091500Z",
      "language": "English",
      "image": "https://www.messengernewspapers.co.uk/resources/images/20661973.jpg?type=og-image",
      "lat": 32.43,
      "lng": 53.69
    },
    {
      "id": "gdelt-420015163",
      "source": "gdelt",
      "category": "humanitarian",
      "title": "The Latest : Trump calls for help to reopen the Strait of Hormuz",
      "country": "",
      "url": "https://www.durangoherald.com/articles/the-latest-trump-calls-for-help-to-reopen-the-strait-of-hormuz/",
      "source_name": "durangoherald.com",
      "timestamp": "20260316T091500Z",
      "language": "English",
      "image": "https://imengine.public.prod.dur.navigacloud.com/?uuid=493fa0ea-0e82-53d3-8d35-ede44b261825&function=fit&type=preview",
      "lat": null,
      "lng": null
    },
    {
      "id": "gdelt-4247950699",
      "source": "gdelt",
      "category": "humanitarian",
      "title": "28ο Φεστιβάλ Κινηματογράφου - Η τεκμηρίωση επιμένει",
      "country": "",
      "url": "https://www.naftemporiki.gr/culture/cinema/2085986/28o-festival-kinimatografoy-i-tekmiriosi-epimenei/",
      "source_name": "naftemporiki.gr",
      "timestamp": "20260316T091500Z",
      "language": "Greek",
      "image": "https://www.naftemporiki.gr/wp-content/uploads/2026/03/festival_ntokimanter_thessalonikis.webp",
      "lat": null,
      "lng": null
    },
    {
      "id": "gdelt-2487346776",
      "source": "gdelt",
      "category": "humanitarian",
      "title": "Ο μηχανισμός στρατηγικών οικονομικών επιπτώσεων του στενού του Ορμούζ",
      "country": "",
      "url": "https://www.epikaira.gr/o-michanismos-stratigikon-oikonomikon-epiptoseon-tou-stenou-tou-ormouz/",
      "source_name": "epikaira.gr",
      "timestamp": "20260316T091500Z",
      "language": "Greek",
      "image": "https://www.epikaira.gr/wp-content/uploads/2026/03/808x454_cmsv2_2e410411-2b04-5f11-919f-4eda3da9053d-3961578.webp",
      "lat": null,
      "lng": null
    },
    {
      "id": "gdelt-85030548",
      "source": "gdelt",
      "category": "humanitarian",
      "title": "Trump warns Nato allies over Iran response as Starmer pledges heating oil help",
      "country": "Iran",
      "url": "https://www.thewestmorlandgazette.co.uk/news/national/25938534.trump-warns-nato-allies-iran-response-starmer-pledges-heating-oil-help/",
      "source_name": "thewestmorlandgazette.co.uk",
      "timestamp": "20260316T091500Z",
      "language": "English",
      "image": "https://www.thewestmorlandgazette.co.uk/resources/images/20661973.jpg?type=og-image",
      "lat": 32.43,
      "lng": 53.69
    },
    {
      "id": "gdelt-1338912435",
      "source": "gdelt",
      "category": "humanitarian",
      "title": "Una UE blindada es prepara per gestionar una altra crisi migratòria",
      "country": "",
      "url": "https://www.elperiodico.cat/ca/internacional/20260316/ue-blindada-prepara-per-gestionar-128004469",
      "source_name": "elperiodico.cat",
      "timestamp": "20260316T091500Z",
      "language": "Catalan",
      "image": "https://estaticos-cdn.prensaiberica.es/clip/d0d5dbbf-ecf2-47b3-9695-b898d37519d3_16-9-aspect-ratio_default_0_x450y168.jpg",
      "lat": null,
      "lng": null
    },
    {
      "id": "gdelt-2147196053",
      "source": "gdelt",
      "category": "humanitarian",
      "title": "Trump warns Nato allies over Iran response as Starmer pledges heating oil help",
      "country": "Iran",
      "url": "https://www.dudleynews.co.uk/news/national/25938534.trump-warns-nato-allies-iran-response-starmer-pledges-heating-oil-help/",
      "source_name": "dudleynews.co.uk",
      "timestamp": "20260316T091500Z",
      "language": "English",
      "image": "https://www.dudleynews.co.uk/resources/images/20661973.jpg?type=og-image",
      "lat": 32.43,
      "lng": 53.69
    },
    {
      "id": "gdelt-4171789265",
      "source": "gdelt",
      "category": "humanitarian",
      "title": "就连日本都委婉拒绝了 ， 高市早苗能躲过特朗普压力吗 ？ ",
      "country": "",
      "url": "https://news.ifeng.com/c/8rXdBfP6vbO",
      "source_name": "news.ifeng.com",
      "timestamp": "20260316T091500Z",
      "language": "Chinese",
      "image": "https://x0.ifengimg.com/ucms/2026_12/A5BA1319ACDB8A524FEF28BC90B4A74B85C9FE16_size55_w600_h337.jpg",
      "lat": null,
      "lng": null
    },
    {
      "id": "gdelt-1359585533",
      "source": "gdelt",
      "category": "humanitarian",
      "title": "Trump warns Nato allies over Iran response as Starmer pledges heating oil help",
      "country": "Iran",
      "url": "https://www.lancashiretelegraph.co.uk/news/national/25938534.trump-warns-nato-allies-iran-response-starmer-pledges-heating-oil-help/",
      "source_name": "lancashiretelegraph.co.uk",
      "timestamp": "20260316T091500Z",
      "language": "English",
      "image": "https://www.lancashiretelegraph.co.uk/resources/images/20661973.jpg?type=og-image",
      "lat": 32.43,
      "lng": 53.69
    },
    {
      "id": "gdelt-3638051975",
      "source": "gdelt",
      "category": "humanitarian",
      "title": "Trump warns Nato allies over Iran response as Starmer pledges heating oil help",
      "country": "Iran",
      "url": "https://www.salisburyjournal.co.uk/news/national/25938534.trump-warns-nato-allies-iran-response-starmer-pledges-heating-oil-help/",
      "source_name": "salisburyjournal.co.uk",
      "timestamp": "20260316T091500Z",
      "language": "English",
      "image": "https://www.salisburyjournal.co.uk/resources/images/20661973.jpg?type=og-image",
      "lat": 32.43,
      "lng": 53.69
    },
    {
      "id": "gdelt-1088608987",
      "source": "gdelt",
      "category": "humanitarian",
      "title": "The Latest : Trump calls for help to reopen the Strait of Hormuz",
      "country": "",
      "url": "https://www.woonsocketcall.com/news/national_and_world_news/the-latest-trump-calls-for-help-to-reopen-the-strait-of-hormuz/article_60304c64-2f0d-5fa3-a5f4-36b0c8e51720.html",
      "source_name": "woonsocketcall.com",
      "timestamp": "20260316T091500Z",
      "language": "English",
      "image": "https://bloximages.newyork1.vip.townnews.com/woonsocketcall.com/content/tncms/custom/image/9c2d53b0-bba9-11ee-bab5-7f9eb3465271.png",
      "lat": null,
      "lng": null
    },
    {
      "id": "gdelt-1805886180",
      "source": "gdelt",
      "category": "humanitarian",
      "title": "Trump warns Nato allies over Iran response as Starmer pledges heating oil help",
      "country": "Iran",
      "url": "https://www.guardian-series.co.uk/news/national/25938534.trump-warns-nato-allies-iran-response-starmer-pledges-heating-oil-help/",
      "source_name": "guardian-series.co.uk",
      "timestamp": "20260316T091500Z",
      "language": "English",
      "image": "https://www.guardian-series.co.uk/resources/images/20661973.jpg?type=og-image",
      "lat": 32.43,
      "lng": 53.69
    },
    {
      "id": "gdelt-1827722356",
      "source": "gdelt",
      "category": "humanitarian",
      "title": "Última hora de la guerra en Oriente Medio | La UE dice que Ormuz está fuera del ámbito de la OTAN",
      "country": "",
      "url": "https://www.elnortedecastilla.es/internacional/oriente-proximo/sigue-directo-ultima-hora-guerra-oriente-medio-20260316165828-dirc.html",
      "source_name": "elnortedecastilla.es",
      "timestamp": "20260316T091500Z",
      "language": "Spanish",
      "image": "https://s2.ppllstatics.com/rc/www/multimedia/2026/03/16/iran-directo-lunes-RDnaTfyRKY0fxbdcNbfvCRN-1200x840@RC.JPG",
      "lat": null,
      "lng": null
    },
    {
      "id": "gdelt-3364400698",
      "source": "gdelt",
      "category": "humanitarian",
      "title": "South Africa Reviews Israel Response in ICJ Genocide Case",
      "country": "Israel",
      "url": "https://briefly.co.za/south-africa/237550-south-africa-reviews-israels-response-icj-genocide-case/",
      "source_name": "briefly.co.za",
      "timestamp": "20260316T091500Z",
      "language": "English",
      "image": "https://cdn.briefly.co.za/images/1200x675/2b5e7f8baada64a6.jpeg?v=1",
      "lat": 31.05,
      "lng": 34.85
    },
    {
      "id": "gdelt-1502653454",
      "source": "gdelt",
      "category": "humanitarian",
      "title": "Trump warns Nato allies over Iran response as Starmer pledges heating oil help",
      "country": "Iran",
      "url": "https://www.wiltshiretimes.co.uk/news/national/25938534.trump-warns-nato-allies-iran-response-starmer-pledges-heating-oil-help/",
      "source_name": "wiltshiretimes.co.uk",
      "timestamp": "20260316T091500Z",
      "language": "English",
      "image": "https://www.wiltshiretimes.co.uk/resources/images/20661973.jpg?type=og-image",
      "lat": 32.43,
      "lng": 53.69
    },
    {
      "id": "gdelt-3852866258",
      "source": "gdelt",
      "category": "humanitarian",
      "title": "Trump warns Nato allies over Iran response as Starmer pledges heating oil help",
      "country": "Iran",
      "url": "https://www.maldonandburnhamstandard.co.uk/news/national/25938534.trump-warns-nato-allies-iran-response-starmer-pledges-heating-oil-help/",
      "source_name": "maldonandburnhamstandard.co.uk",
      "timestamp": "20260316T091500Z",
      "language": "English",
      "image": "https://www.maldonandburnhamstandard.co.uk/resources/images/20661973.jpg?type=og-image",
      "lat": 32.43,
      "lng": 53.69
    },
    {
      "id": "gdelt-1241384464",
      "source": "gdelt",
      "category": "humanitarian",
      "title": "Trump warns Nato allies over Iran response as Starmer pledges heating oil help",
      "country": "Iran",
      "url": "https://www.thisiswiltshire.co.uk/news/national/25938534.trump-warns-nato-allies-iran-response-starmer-pledges-heating-oil-help/",
      "source_name": "thisiswiltshire.co.uk",
      "timestamp": "20260316T091500Z",
      "language": "English",
      "image": "https://www.thisiswiltshire.co.uk/resources/images/20661973.jpg?type=og-image",
      "lat": 32.43,
      "lng": 53.69
    },
    {
      "id": "gdelt-1639631534",
      "source": "gdelt",
      "category": "humanitarian",
      "title": "Kakav je to natpis nosio španjolski glumac na dodjeli Oscara ? ",
      "country": "",
      "url": "https://www.index.hr/magazin/clanak/kakav-je-to-natpis-nosio-spanjolski-glumac-na-dodjeli-oscara/2771570.aspx",
      "source_name": "index.hr",
      "timestamp": "20260316T091500Z",
      "language": "Croatian",
      "image": "https://ip.index.hr/remote/bucket.index.hr/b/index/343fab87-bab1-4b3f-91f0-d22d14e93bf4.png?fb_wtrmrk=magazin.jpg&mode=crop&format=png",
      "lat": null,
      "lng": null
    },
    {
      "id": "gdelt-675692907",
      "source": "gdelt",
      "category": "humanitarian",
      "title": "Trump warns Nato allies over Iran response as Starmer pledges heating oil help",
      "country": "Iran",
      "url": "https://www.cotswoldjournal.co.uk/news/national/25938534.trump-warns-nato-allies-iran-response-starmer-pledges-heating-oil-help/",
      "source_name": "cotswoldjournal.co.uk",
      "timestamp": "20260316T091500Z",
      "language": "English",
      "image": "https://www.cotswoldjournal.co.uk/resources/images/20661973.jpg?type=og-image",
      "lat": 32.43,
      "lng": 53.69
    },
    {
      "id": "gdelt-3386977010",
      "source": "gdelt",
      "category": "humanitarian",
      "title": "Trump warns Nato allies over Iran response as Starmer pledges heating oil help",
      "country": "Iran",
      "url": "https://www.somersetcountygazette.co.uk/news/national/25938534.trump-warns-nato-allies-iran-response-starmer-pledges-heating-oil-help/",
      "source_name": "somersetcountygazette.co.uk",
      "timestamp": "20260316T091500Z",
      "language": "English",
      "image": "https://www.somersetcountygazette.co.uk/resources/images/20661973.jpg?type=og-image",
      "lat": 32.43,
      "lng": 53.69
    },
    {
      "id": "gdelt-3726937091",
      "source": "gdelt",
      "category": "humanitarian",
      "title": "Batý  ya tepki Mazlumun yanýnda duran þerefli Türkiyeyi seviyorum",
      "country": "",
      "url": "https://www.star.com.tr/dunya/batiya-tepki-mazlumun-yaninda-duran-serefli-turkiyeyi-seviyorum-haber-2003395/",
      "source_name": "star.com.tr",
      "timestamp": "20260316T091500Z",
      "language": "Turkish",
      "image": "https://imgs.stargazete.com/imgsdisk/2026/03/16/batiya-tepki-mazlumun-yan-373_2-41.jpg",
      "lat": null,
      "lng": null
    },
    {
      "id": "gdelt-3809538816",
      "source": "gdelt",
      "category": "humanitarian",
      "title": "Sir Keir Starmer announces new cost of living support as prices soar",
      "country": "",
      "url": "https://www.hulldailymail.co.uk/news/cost-of-living/sir-keir-starmer-announces-new-10868790",
      "source_name": "hulldailymail.co.uk",
      "timestamp": "20260316T091500Z",
      "language": "English",
      "image": "https://i2-prod.devonlive.com/news/uk-world-news/article10868791.ece/ALTERNATES/s1200/0_GettyImages-2265614495.jpg",
      "lat": null,
      "lng": null
    },
    {
      "id": "gdelt-3513478455",
      "source": "gdelt",
      "category": "humanitarian",
      "title": "İsrailin yerinden ettiği Lübnanlılar , Batı  nın sessizliği ve İsraille işbirliğinden şikayetçi",
      "country": "",
      "url": "https://www.haberler.com/guncel/lubnan-da-israil-saldirilari-nedeniyle-yerinden-edilenler-zor-kosullarda-yasiyor-19661964-haberi/",
      "source_name": "haberler.com",
      "timestamp": "20260316T091500Z",
      "language": "Turkish",
      "image": "https://foto.haberler.com/haber/2026/02/11/israil-in-yerinden-ettigi-lubnanlilar-bati-ni-19661964_amp.jpg",
      "lat": null,
      "lng": null
    },
    {
      "id": "gdelt-3383710155",
      "source": "gdelt",
      "category": "humanitarian",
      "title": "Libano , lindifferenza del governo per le vittime degli attacchi israeliani",
      "country": "Israel",
      "url": "https://www.ilfattoquotidiano.it/2026/03/16/libano-lindifferenza-del-governo-per-le-vittime-degli-attacchi-israeliani/8321478/",
      "source_name": "ilfattoquotidiano.it",
      "timestamp": "20260316T091500Z",
      "language": "Italian",
      "image": "https://st.ilfattoquotidiano.it/wp-content/img/autori/RNoury.jpg",
      "lat": 31.05,
      "lng": 34.85
    },
    {
      "id": "gdelt-1988890632",
      "source": "gdelt",
      "category": "humanitarian",
      "title": "Гинтаутас Мажейкис . Станет ли Иран несостоявшимся государством ? ",
      "country": "",
      "url": "https://www.lrt.lt/ru/novosti/17/2869078/gintautas-mazheikis-stanet-li-iran-nesostoiavshimsia-gosudarstvom",
      "source_name": "lrt.lt",
      "timestamp": "20260316T091500Z",
      "language": "Russian",
      "image": "https://www.lrt.lt/img/2025/02/26/2004065-320085-1287x836.jpg",
      "lat": null,
      "lng": null
    },
    {
      "id": "gdelt-100978758",
      "source": "gdelt",
      "category": "humanitarian",
      "title": "Yeditepe Üniversitesinde mescit erişimi ve iftar organizasyonu tartışma konusu oldu",
      "country": "",
      "url": "http://www.haberler.com/guncel/yeditepe-universitesi-nde-mescit-erisimi-ve-iftar-19662070-haberi/",
      "source_name": "haberler.com",
      "timestamp": "20260316T091500Z",
      "language": "Turkish",
      "image": "",
      "lat": null,
      "lng": null
    },
    {
      "id": "gdelt-3145378551",
      "source": "gdelt",
      "category": "humanitarian",
      "title": "Όσκαρ 2026 : Οι αναφορές στο σκάνδαλο Έπσταϊν , ο Τραμπ και τα μηνύματα για τον πόλεμο",
      "country": "",
      "url": "https://www.eleftherostypos.gr/cinematv/oskar-2026-oi-anafores-sto-skandalo-epstain-o-trab-kai-ta-minymata-gia-ton-polemo",
      "source_name": "eleftherostypos.gr",
      "timestamp": "20260316T091500Z",
      "language": "Greek",
      "image": "https://www.eleftherostypos.gr/wp-content/uploads/2026/03/oscar-javier-bardem-scaled.jpg",
      "lat": null,
      "lng": null
    },
    {
      "id": "gdelt-3088022736",
      "source": "gdelt",
      "category": "humanitarian",
      "title": "Iran - Krieg im Liveticker : +++ 09 : 35 Israel meldet Zerstörung von Chameneis Flugzeug +++",
      "country": "Israel",
      "url": "https://www.n-tv.de/politik/09-35-Israel-meldet-Zerstoerung-von-Chameneis-Flugzeug-id30415311.html",
      "source_name": "n-tv.de",
      "timestamp": "20260316T091500Z",
      "language": "German",
      "image": "https://www.n-tv.de/img/30469482/1773429839/Img_16_9/1200/imago850457507.jpg",
      "lat": 31.05,
      "lng": 34.85
    },
    {
      "id": "gdelt-2496703601",
      "source": "gdelt",
      "category": "humanitarian",
      "title": "Trump warns Nato allies over Iran response as Starmer pledges heating oil help",
      "country": "Iran",
      "url": "https://www.thenorthernecho.co.uk/news/national/25938534.trump-warns-nato-allies-iran-response-starmer-pledges-heating-oil-help/",
      "source_name": "thenorthernecho.co.uk",
      "timestamp": "20260316T091500Z",
      "language": "English",
      "image": "https://www.thenorthernecho.co.uk/resources/images/20661973.jpg?type=og-image",
      "lat": 32.43,
      "lng": 53.69
    },
    {
      "id": "gdelt-2794036269",
      "source": "gdelt",
      "category": "humanitarian",
      "title": "The Latest : Trump calls for allies to help reopen Strait of Hormuz",
      "country": "",
      "url": "https://www.wboc.com/news/international/the-latest-trump-calls-for-allies-to-help-reopen-strait-of-hormuz/article_e2be37d8-127d-519f-bffa-2df907cf091a.html",
      "source_name": "wboc.com",
      "timestamp": "20260316T091500Z",
      "language": "English",
      "image": "https://bloximages.newyork1.vip.townnews.com/wboc.com/content/tncms/assets/v3/editorial/b/49/b49e6da3-e726-544c-8b76-9528c72bca00/69b796b3d9231.image.jpg?crop=1763%2C926%2C0%2C124",
      "lat": null,
      "lng": null
    },
    {
      "id": "gdelt-821311285",
      "source": "gdelt",
      "category": "humanitarian",
      "title": "Sir Keir Starmer announces new cost of living support as prices soar",
      "country": "",
      "url": "https://www.somersetlive.co.uk/news/cost-of-living/sir-keir-starmer-announces-new-10868790",
      "source_name": "somersetlive.co.uk",
      "timestamp": "20260316T090000Z",
      "language": "English",
      "image": "https://i2-prod.devonlive.com/news/uk-world-news/article10868791.ece/ALTERNATES/s1200/0_GettyImages-2265614495.jpg",
      "lat": null,
      "lng": null
    },
    {
      "id": "gdelt-3699336540",
      "source": "gdelt",
      "category": "humanitarian",
      "title": "کارشناس : متأسفانه ، عامل سیاسی بر کار دادگاه کیفری بین‌المللی تأثیر می‌گذارد",
      "country": "",
      "url": "https://spnfa.ir/20260316/28688257.html",
      "source_name": "spnfa.ir",
      "timestamp": "20260316T090000Z",
      "language": "Persian",
      "image": "https://cdn1.img.spnfa.ir/img/07ea/03/10/28688103_1:0:799:449_2072x0_60_0_0_65c002bfe441093ae153a645f5bce180.jpg",
      "lat": null,
      "lng": null
    }
  ]
}