{
  "total_events": 160,
  "by_source": {
    "acled": 0,
    "gdelt": 95,
    "firms": 61,
    "usgs": 4,
    "reliefweb": 0
  },
  "by_category": {
    "conflict": 50,
    "protest": 45,
    "thermal_anomaly": 61,
    "earthquake": 4
  },
  "by_country": {
    "Iran": 23,
    "Iraq": 4,
    "Tehran": 4,
    "Israel": 12
  },
  "last_updated": "2026-03-13T12:22:46.327599Z",
  "feed_freshness": {
    "acled": {
      "count": 0,
      "fetched_at": "2026-03-13T12:15:08.547531Z"
    },
    "gdelt": {
      "count": 95,
      "fetched_at": "2026-03-13T12:20:21.494723Z"
    },
    "firms": {
      "count": 61,
      "fetched_at": "2026-03-13T11:27:48.292646Z"
    },
    "usgs": {
      "count": 4,
      "fetched_at": "2026-03-13T12:21:48.825182Z"
    },
    "reliefweb": {
      "count": 0,
      "fetched_at": "2026-03-13T12:05:45.821287Z"
    }
  }
}